[{"fingerprint":{"pressure":-1.0,"wifi":{"2c:36:f8:0f:da:93":{"SSID":"utroam-1x","capabilities":"[WPA2-EAP-CCMP][ESS]","timestamp":13442082534,"level":-81,"frequency":2462},"2c:36:f8:0f:f5:15":{"SSID":"eng.ut-1x","capabilities":"[WPA2-EAP-CCMP][ESS]","timestamp":13442082660,"level":-80,"frequency":2462},"3c:ce:73:49:7a:00":{"SSID":"eng.ut","capabilities":"[WPA2-PSK-CCMP][ESS]","timestamp":13442082130,"level":-76,"frequency":2412},"2c:36:f8:0f:f5:13":{"SSID":"utroam-1x","capabilities":"[WPA2-EAP-CCMP][ESS]","timestamp":13442082561,"level":-75,"frequency":2462},"2c:36:f8:0e:6b:27":{"SSID":"ist_members","capabilities":"[WPA2-PSK-CCMP][ESS]","timestamp":13442082468,"level":-56,"frequency":2437},"2c:36:f8:0e:6b:28":{"SSID":"eng.ut-guest","capabilities":"[ESS]","timestamp":13442082414,"level":-59,"frequency":2437},"00:24:14:ff:f4:b1":{"SSID":"UTnet-wireless","capabilities":"[WPA2-PSK-CCMP][ESS]","timestamp":13442082600,"level":-64,"frequency":2462},"00:24:14:ff:f4:b2":{"SSID":"0001softbank","capabilities":"[ESS]","timestamp":13442082574,"level":-63,"frequency":2462},"2c:36:f8:0f:d3:22":{"SSID":"utroam","capabilities":"[WPA-PSK-CCMP][WPA2-PSK-CCMP][ESS]","timestamp":13442082521,"level":-71,"frequency":2437},"2c:36:f8:0e:6b:26":{"SSID":"sanshiro","capabilities":"[WPA2-PSK-CCMP][ESS]","timestamp":13442082451,"level":-56,"frequency":2437},"2c:36:f8:0f:d3:23":{"SSID":"utroam-1x","capabilities":"[WPA2-EAP-CCMP][ESS]","timestamp":13442082439,"level":-64,"frequency":2437},"00:24:14:ff:f4:b0":{"SSID":"","capabilities":"[WEP][ESS]","timestamp":13442082311,"level":-60,"frequency":2462},"00:24:14:ff:f4:b5":{"SSID":"Wi2_club","capabilities":"[WPA2-PSK-CCMP][ESS]","timestamp":13442082481,"level":-63,"frequency":2462},"00:24:14:ff:f4:b6":{"SSID":"docomo","capabilities":"[WEP][ESS]","timestamp":13442082388,"level":-61,"frequency":2462},"2c:36:f8:0e:6b:22":{"SSID":"utroam","capabilities":"[WPA-PSK-CCMP][WPA2-PSK-CCMP][ESS]","timestamp":13442082495,"level":-56,"frequency":2437},"00:24:14:ff:f4:b3":{"SSID":"SWS1day","capabilities":"[ESS]","timestamp":13442082227,"level":-62,"frequency":2462},"2c:36:f8:0f:d3:28":{"SSID":"eng.ut-guest","capabilities":"[ESS]","timestamp":13442082508,"level":-66,"frequency":2437},"00:24:14:ff:f4:b4":{"SSID":"Wi2","capabilities":"[ESS]","timestamp":13442082324,"level":-61,"frequency":2462},"2c:36:f8:0e:6b:20":{"SSID":"eng.ut","capabilities":"[WPA2-PSK-CCMP][ESS]","timestamp":13442082402,"level":-57,"frequency":2437},"2c:36:f8:0f:ff:a0":{"SSID":"eng.ut","capabilities":"[WPA2-PSK-CCMP][ESS]","timestamp":13442082259,"level":-49,"frequency":2462},"2c:36:f8:0f:ff:a4":{"SSID":"bld2-guest","capabilities":"[WEP][ESS]","timestamp":13442082285,"level":-49,"frequency":2462},"2c:36:f8:0f:ff:a3":{"SSID":"utroam-1x","capabilities":"[WPA2-EAP-CCMP][ESS]","timestamp":13442082613,"level":-50,"frequency":2462},"2c:36:f8:0f:ff:a2":{"SSID":"utroam","capabilities":"[WPA-PSK-CCMP][WPA2-PSK-CCMP][ESS]","timestamp":13442082338,"level":-48,"frequency":2462},"2c:36:f8:0f:ff:a8":{"SSID":"eng.ut-guest","capabilities":"[ESS]","timestamp":13442082271,"level":-49,"frequency":2462},"2c:36:f8:0f:ff:a7":{"SSID":"ist_members","capabilities":"[WPA2-PSK-CCMP][ESS]","timestamp":13442082587,"level":-49,"frequency":2462},"2c:36:f8:0f:ff:a6":{"SSID":"sanshiro","capabilities":"[WPA2-PSK-CCMP][ESS]","timestamp":13442082363,"level":-49,"frequency":2462},"2c:36:f8:0f:ff:a5":{"SSID":"eng.ut-1x","capabilities":"[WPA2-EAP-CCMP][ESS]","timestamp":13442082647,"level":-51,"frequency":2462},"00:16:01:04:28:d4":{"SSID":"SYSTEM6DESKWORKROOM","capabilities":"[WPA2-PSK-CCMP][ESS]","timestamp":13442082699,"level":-83,"frequency":2472},"00:07:40:a0:8b:8e":{"SSID":"00074096666C","capabilities":"[ESS]","timestamp":13442082685,"level":-92,"frequency":2462},"2c:36:f8:60:23:50":{"SSID":"eng.ut","capabilities":"[WPA2-PSK-CCMP][ESS]","timestamp":13442082351,"level":-52,"frequency":2462},"2c:36:f8:60:23:56":{"SSID":"sanshiro","capabilities":"[WPA2-PSK-CCMP][ESS]","timestamp":13442082214,"level":-55,"frequency":2462},"2c:36:f8:60:23:57":{"SSID":"ist_members","capabilities":"[WPA2-PSK-CCMP][ESS]","timestamp":13442082240,"level":-53,"frequency":2462},"2c:36:f8:60:23:58":{"SSID":"eng.ut-guest","capabilities":"[ESS]","timestamp":13442082375,"level":-52,"frequency":2462},"02:1a:11:f3:5d:60":{"SSID":"N7HK_AndroidAP","capabilities":"[WPA2-PSK-CCMP][ESS]","timestamp":13442082427,"level":-62,"frequency":2437},"2c:36:f8:60:23:52":{"SSID":"utroam","capabilities":"[WPA-PSK-CCMP][WPA2-PSK-CCMP][ESS]","timestamp":13442082017,"level":-54,"frequency":2462},"2c:36:f8:60:23:53":{"SSID":"utroam-1x","capabilities":"[WPA2-EAP-CCMP][ESS]","timestamp":13442082548,"level":-57,"frequency":2462},"2c:36:f8:60:23:54":{"SSID":"bld2-guest","capabilities":"[WEP][ESS]","timestamp":13442082187,"level":-51,"frequency":2462},"2c:36:f8:60:23:55":{"SSID":"eng.ut-1x","capabilities":"[WPA2-EAP-CCMP][ESS]","timestamp":13442082674,"level":-58,"frequency":2462},"2c:36:f8:0f:64:37":{"SSID":"ist_members","capabilities":"[WPA2-PSK-CCMP][ESS]","timestamp":13442082042,"level":-55,"frequency":2412},"2c:36:f8:0f:64:38":{"SSID":"eng.ut-guest","capabilities":"[ESS]","timestamp":13442082174,"level":-53,"frequency":2412},"2c:36:f8:60:0f:70":{"SSID":"eng.ut","capabilities":"[WPA2-PSK-CCMP][ESS]","timestamp":13442082071,"level":-61,"frequency":2412},"2c:36:f8:0f:64:35":{"SSID":"eng.ut-1x","capabilities":"[WPA2-EAP-CCMP][ESS]","timestamp":13442082144,"level":-53,"frequency":2412},"2c:36:f8:0f:64:36":{"SSID":"sanshiro","capabilities":"[WPA2-PSK-CCMP][ESS]","timestamp":13442082298,"level":-57,"frequency":2412},"2c:36:f8:0f:64:33":{"SSID":"utroam-1x","capabilities":"[WPA2-EAP-CCMP][ESS]","timestamp":13442082087,"level":-53,"frequency":2412},"00:24:14:ff:f4:b7":{"SSID":"0000docomo","capabilities":"[WPA2-PSK-CCMP][ESS]","timestamp":13442082200,"level":-60,"frequency":2462},"2c:36:f8:60:0f:76":{"SSID":"sanshiro","capabilities":"[WPA2-PSK-CCMP][ESS]","timestamp":13442082056,"level":-60,"frequency":2412},"2c:36:f8:60:0f:74":{"SSID":"bld2-guest","capabilities":"[WEP][ESS]","timestamp":13442082102,"level":-60,"frequency":2412},"2c:36:f8:60:0f:72":{"SSID":"utroam","capabilities":"[WPA-PSK-CCMP][WPA2-PSK-CCMP][ESS]","timestamp":13442082115,"level":-69,"frequency":2412},"2c:36:f8:0f:64:30":{"SSID":"eng.ut","capabilities":"[WPA2-PSK-CCMP][ESS]","timestamp":13442082159,"level":-54,"frequency":2412},"00:07:40:fe:2e:c7":{"SSID":"","capabilities":"[WPA-PSK-CCMP][ESS]","timestamp":13442082626,"level":-88,"frequency":2462}},"magnetic":{"x":-4.666383,"y":2.4998477,"z":33.83127},"gravity":{"x":0.120159,"y":7.339425,"z":6.5028014}},"location":{"floor":"3F","accuracy":0.5,"latitude":35.7144511312929,"longitude":139.76177360862494}},{"fingerprint":{"pressure":-1.0,"wifi":{"2c:36:f8:0f:da:95":{"SSID":"eng.ut-1x","capabilities":"[WPA2-EAP-CCMP][ESS]","timestamp":13450488501,"level":-80,"frequency":2462},"2c:36:f8:0f:da:93":{"SSID":"utroam-1x","capabilities":"[WPA2-EAP-CCMP][ESS]","timestamp":13442082534,"level":-81,"frequency":2462},"2c:36:f8:0f:f5:15":{"SSID":"eng.ut-1x","capabilities":"[WPA2-EAP-CCMP][ESS]","timestamp":13442082660,"level":-80,"frequency":2462},"2c:36:f8:0f:f5:17":{"SSID":"ist_members","capabilities":"[WPA2-PSK-CCMP][ESS]","timestamp":13450489109,"level":-77,"frequency":2462},"3c:ce:73:49:7a:00":{"SSID":"eng.ut","capabilities":"[WPA2-PSK-CCMP][ESS]","timestamp":13450488328,"level":-76,"frequency":2412},"3c:ce:73:49:7a:02":{"SSID":"utroam-1x","capabilities":"[WPA2-EAP-CCMP][ESS]","timestamp":13450488382,"level":-74,"frequency":2412},"2c:36:f8:0f:f5:10":{"SSID":"eng.ut","capabilities":"[WPA2-PSK-CCMP][ESS]","timestamp":13450489023,"level":-75,"frequency":2462},"3c:ce:73:49:7a:04":{"SSID":"bld2-guest","capabilities":"[WEP][ESS]","timestamp":13450488349,"level":-75,"frequency":2412},"2c:36:f8:0f:f5:13":{"SSID":"utroam-1x","capabilities":"[WPA2-EAP-CCMP][ESS]","timestamp":13442082561,"level":-75,"frequency":2462},"2c:36:f8:0e:6b:27":{"SSID":"ist_members","capabilities":"[WPA2-PSK-CCMP][ESS]","timestamp":13450488932,"level":-57,"frequency":2437},"3c:ce:73:49:7a:03":{"SSID":"ist_members","capabilities":"[WPA2-PSK-CCMP][ESS]","timestamp":13450488437,"level":-77,"frequency":2412},"2c:36:f8:0e:6b:28":{"SSID":"eng.ut-guest","capabilities":"[ESS]","timestamp":13450488739,"level":-56,"frequency":2437},"00:24:14:ff:f4:b1":{"SSID":"UTnet-wireless","capabilities":"[WPA2-PSK-CCMP][ESS]","timestamp":13450488666,"level":-63,"frequency":2462},"00:24:14:ff:f4:b2":{"SSID":"0001softbank","capabilities":"[ESS]","timestamp":13450488633,"level":-61,"frequency":2462},"2c:36:f8:0f:d3:22":{"SSID":"utroam","capabilities":"[WPA-PSK-CCMP][WPA2-PSK-CCMP][ESS]","timestamp":13450488906,"level":-72,"frequency":2437},"2c:36:f8:0e:6b:26":{"SSID":"sanshiro","capabilities":"[WPA2-PSK-CCMP][ESS]","timestamp":13450488893,"level":-55,"frequency":2437},"2c:36:f8:0f:d3:23":{"SSID":"utroam-1x","capabilities":"[WPA2-EAP-CCMP][ESS]","timestamp":13442082439,"level":-64,"frequency":2437},"2c:36:f8:0e:6b:24":{"SSID":"bld2-guest","capabilities":"[WEP][ESS]","timestamp":13450488863,"level":-56,"frequency":2437},"00:24:14:ff:f4:b0":{"SSID":"","capabilities":"[WEP][ESS]","timestamp":13450488990,"level":-62,"frequency":2462},"00:24:14:ff:f4:b5":{"SSID":"Wi2_club","capabilities":"[WPA2-PSK-CCMP][ESS]","timestamp":13450488948,"level":-59,"frequency":2462},"2c:36:f8:0f:f5:18":{"SSID":"eng.ut-guest","capabilities":"[ESS]","timestamp":13450489037,"level":-74,"frequency":2462},"00:24:14:ff:f4:b6":{"SSID":"docomo","capabilities":"[WEP][ESS]","timestamp":13450489051,"level":-66,"frequency":2462},"2c:36:f8:0e:6b:22":{"SSID":"utroam","capabilities":"[WPA-PSK-CCMP][WPA2-PSK-CCMP][ESS]","timestamp":13450488879,"level":-56,"frequency":2437},"00:24:14:ff:f4:b3":{"SSID":"SWS1day","capabilities":"[ESS]","timestamp":13450488710,"level":-64,"frequency":2462},"2c:36:f8:0f:d3:28":{"SSID":"eng.ut-guest","capabilities":"[ESS]","timestamp":13442082508,"level":-66,"frequency":2437},"00:24:14:ff:f4:b4":{"SSID":"Wi2","capabilities":"[ESS]","timestamp":13450488552,"level":-60,"frequency":2462},"2c:36:f8:0e:6b:20":{"SSID":"eng.ut","capabilities":"[WPA2-PSK-CCMP][ESS]","timestamp":13450488846,"level":-56,"frequency":2437},"2c:36:f8:0f:ff:a0":{"SSID":"eng.ut","capabilities":"[WPA2-PSK-CCMP][ESS]","timestamp":13450488292,"level":-43,"frequency":2462},"2c:36:f8:0f:ff:a4":{"SSID":"bld2-guest","capabilities":"[WEP][ESS]","timestamp":13450488538,"level":-44,"frequency":2462},"2c:36:f8:0f:ff:a3":{"SSID":"utroam-1x","capabilities":"[WPA2-EAP-CCMP][ESS]","timestamp":13450488694,"level":-44,"frequency":2462},"2c:36:f8:0f:ff:a2":{"SSID":"utroam","capabilities":"[WPA-PSK-CCMP][WPA2-PSK-CCMP][ESS]","timestamp":13450488572,"level":-44,"frequency":2462},"2c:36:f8:0f:ff:a8":{"SSID":"eng.ut-guest","capabilities":"[ESS]","timestamp":13450488518,"level":-44,"frequency":2462},"2c:36:f8:0f:ff:a7":{"SSID":"ist_members","capabilities":"[WPA2-PSK-CCMP][ESS]","timestamp":13450488679,"level":-46,"frequency":2462},"2c:36:f8:0f:ff:a6":{"SSID":"sanshiro","capabilities":"[WPA2-PSK-CCMP][ESS]","timestamp":13450488588,"level":-44,"frequency":2462},"2c:36:f8:0f:ff:a5":{"SSID":"eng.ut-1x","capabilities":"[WPA2-EAP-CCMP][ESS]","timestamp":13450488724,"level":-44,"frequency":2462},"00:16:01:04:28:d4":{"SSID":"SYSTEM6DESKWORKROOM","capabilities":"[WPA2-PSK-CCMP][ESS]","timestamp":13442082699,"level":-83,"frequency":2472},"10:c6:1f:eb:a8:8e":{"SSID":"GL01P-10C61FEBA88E","capabilities":"[WPA-PSK-TKIP][WPA2-PSK-CCMP+TKIP][WPS][ESS]","timestamp":13450488418,"level":-70,"frequency":2422},"00:07:40:a0:8b:8e":{"SSID":"00074096666C","capabilities":"[ESS]","timestamp":13442082685,"level":-92,"frequency":2462},"2c:36:f8:60:23:50":{"SSID":"eng.ut","capabilities":"[WPA2-PSK-CCMP][ESS]","timestamp":13450488603,"level":-53,"frequency":2462},"2c:36:f8:60:23:56":{"SSID":"sanshiro","capabilities":"[WPA2-PSK-CCMP][ESS]","timestamp":13450489096,"level":-53,"frequency":2462},"2c:36:f8:60:23:57":{"SSID":"ist_members","capabilities":"[WPA2-PSK-CCMP][ESS]","timestamp":13450488963,"level":-52,"frequency":2462},"2c:36:f8:60:23:58":{"SSID":"eng.ut-guest","capabilities":"[ESS]","timestamp":13450488618,"level":-53,"frequency":2462},"02:1a:11:f3:5d:60":{"SSID":"N7HK_AndroidAP","capabilities":"[WPA2-PSK-CCMP][ESS]","timestamp":13442082427,"level":-62,"frequency":2437},"2c:36:f8:60:23:52":{"SSID":"utroam","capabilities":"[WPA-PSK-CCMP][WPA2-PSK-CCMP][ESS]","timestamp":13450489066,"level":-53,"frequency":2462},"2c:36:f8:60:23:53":{"SSID":"utroam-1x","capabilities":"[WPA2-EAP-CCMP][ESS]","timestamp":13450488976,"level":-52,"frequency":2462},"2c:36:f8:60:23:54":{"SSID":"bld2-guest","capabilities":"[WEP][ESS]","timestamp":13450488650,"level":-52,"frequency":2462},"2c:36:f8:60:23:55":{"SSID":"eng.ut-1x","capabilities":"[WPA2-EAP-CCMP][ESS]","timestamp":13450489007,"level":-53,"frequency":2462},"2c:36:f8:0f:64:37":{"SSID":"ist_members","capabilities":"[WPA2-PSK-CCMP][ESS]","timestamp":13442082042,"level":-55,"frequency":2412},"2c:36:f8:0f:64:38":{"SSID":"eng.ut-guest","capabilities":"[ESS]","timestamp":13450488397,"level":-55,"frequency":2412},"2c:36:f8:60:0f:70":{"SSID":"eng.ut","capabilities":"[WPA2-PSK-CCMP][ESS]","timestamp":13450488453,"level":-56,"frequency":2412},"2c:36:f8:0f:64:35":{"SSID":"eng.ut-1x","capabilities":"[WPA2-EAP-CCMP][ESS]","timestamp":13442082144,"level":-53,"frequency":2412},"2c:36:f8:0f:64:36":{"SSID":"sanshiro","capabilities":"[WPA2-PSK-CCMP][ESS]","timestamp":13442082298,"level":-57,"frequency":2412},"2c:36:f8:0f:64:33":{"SSID":"utroam-1x","capabilities":"[WPA2-EAP-CCMP][ESS]","timestamp":13442082087,"level":-53,"frequency":2412},"00:24:14:ff:f4:b7":{"SSID":"0000docomo","capabilities":"[WPA2-PSK-CCMP][ESS]","timestamp":13450489082,"level":-63,"frequency":2462},"2c:36:f8:0f:d3:20":{"SSID":"eng.ut","capabilities":"[WPA2-PSK-CCMP][ESS]","timestamp":13450488919,"level":-80,"frequency":2437},"2c:36:f8:60:0f:76":{"SSID":"sanshiro","capabilities":"[WPA2-PSK-CCMP][ESS]","timestamp":13442082056,"level":-60,"frequency":2412},"2c:36:f8:60:0f:74":{"SSID":"bld2-guest","capabilities":"[WEP][ESS]","timestamp":13450488469,"level":-59,"frequency":2412},"2c:36:f8:60:0f:72":{"SSID":"utroam","capabilities":"[WPA-PSK-CCMP][WPA2-PSK-CCMP][ESS]","timestamp":13450488486,"level":-59,"frequency":2412},"2c:36:f8:0f:64:30":{"SSID":"eng.ut","capabilities":"[WPA2-PSK-CCMP][ESS]","timestamp":13450488364,"level":-54,"frequency":2412},"00:07:40:fe:2e:c7":{"SSID":"","capabilities":"[WPA-PSK-CCMP][ESS]","timestamp":13442082626,"level":-88,"frequency":2462}},"magnetic":{"x":-26.34822,"y":-0.3168174,"z":27.36466},"gravity":{"x":0.09322423,"y":6.8435264,"z":7.023241}},"location":{"floor":"3F","accuracy":0.5,"latitude":35.714463381320854,"longitude":139.7618393227458}},{"fingerprint":{"pressure":-1.0,"wifi":{"2c:36:f8:0f:da:90":{"SSID":"eng.ut","capabilities":"[WPA2-PSK-CCMP][ESS]","timestamp":13462354877,"level":-80,"frequency":2462},"2c:36:f8:0f:fb:80":{"SSID":"eng.ut","capabilities":"[WPA2-PSK-CCMP][ESS]","timestamp":13462354721,"level":-83,"frequency":2412},"2c:36:f8:0f:da:95":{"SSID":"eng.ut-1x","capabilities":"[WPA2-EAP-CCMP][ESS]","timestamp":13450488501,"level":-80,"frequency":2462},"2c:36:f8:0f:f5:14":{"SSID":"bld2-guest","capabilities":"[WEP][ESS]","timestamp":13462354865,"level":-74,"frequency":2462},"2c:36:f8:0f:f5:17":{"SSID":"ist_members","capabilities":"[WPA2-PSK-CCMP][ESS]","timestamp":13462354853,"level":-74,"frequency":2462},"3c:ce:73:49:7a:00":{"SSID":"eng.ut","capabilities":"[WPA2-PSK-CCMP][ESS]","timestamp":13450488328,"level":-76,"frequency":2412},"3c:ce:73:49:7a:02":{"SSID":"utroam-1x","capabilities":"[WPA2-EAP-CCMP][ESS]","timestamp":13450488382,"level":-74,"frequency":2412},"2c:36:f8:0f:f5:10":{"SSID":"eng.ut","capabilities":"[WPA2-PSK-CCMP][ESS]","timestamp":13462354773,"level":-74,"frequency":2462},"3c:ce:73:49:7a:04":{"SSID":"bld2-guest","capabilities":"[WEP][ESS]","timestamp":13450488349,"level":-75,"frequency":2412},"2c:36:f8:0e:6b:27":{"SSID":"ist_members","capabilities":"[WPA2-PSK-CCMP][ESS]","timestamp":13450488932,"level":-57,"frequency":2437},"2c:36:f8:0f:f5:12":{"SSID":"utroam","capabilities":"[WPA-PSK-CCMP][WPA2-PSK-CCMP][ESS]","timestamp":13462354882,"level":-75,"frequency":2462},"3c:ce:73:49:7a:03":{"SSID":"ist_members","capabilities":"[WPA2-PSK-CCMP][ESS]","timestamp":13450488437,"level":-77,"frequency":2412},"2c:36:f8:0e:6b:28":{"SSID":"eng.ut-guest","capabilities":"[ESS]","timestamp":13462354804,"level":-74,"frequency":2437},"00:24:14:ff:f4:b1":{"SSID":"UTnet-wireless","capabilities":"[WPA2-PSK-CCMP][ESS]","timestamp":13450488666,"level":-63,"frequency":2462},"00:24:14:ff:f4:b2":{"SSID":"0001softbank","capabilities":"[ESS]","timestamp":13450488633,"level":-61,"frequency":2462},"2c:36:f8:0f:d3:22":{"SSID":"utroam","capabilities":"[WPA-PSK-CCMP][WPA2-PSK-CCMP][ESS]","timestamp":13450488906,"level":-72,"frequency":2437},"2c:36:f8:0e:6b:26":{"SSID":"sanshiro","capabilities":"[WPA2-PSK-CCMP][ESS]","timestamp":13450488893,"level":-55,"frequency":2437},"2c:36:f8:0e:6b:24":{"SSID":"bld2-guest","capabilities":"[WEP][ESS]","timestamp":13462354810,"level":-76,"frequency":2437},"00:24:14:ff:f4:b0":{"SSID":"","capabilities":"[WEP][ESS]","timestamp":13450488990,"level":-62,"frequency":2462},"00:24:14:ff:f4:b5":{"SSID":"Wi2_club","capabilities":"[WPA2-PSK-CCMP][ESS]","timestamp":13462354685,"level":-66,"frequency":2462},"2c:36:f8:0f:f5:18":{"SSID":"eng.ut-guest","capabilities":"[ESS]","timestamp":13462354859,"level":-74,"frequency":2462},"00:24:14:ff:f4:b6":{"SSID":"docomo","capabilities":"[WEP][ESS]","timestamp":13462354786,"level":-65,"frequency":2462},"2c:36:f8:0e:6b:22":{"SSID":"utroam","capabilities":"[WPA-PSK-CCMP][WPA2-PSK-CCMP][ESS]","timestamp":13450488879,"level":-56,"frequency":2437},"00:24:14:ff:f4:b3":{"SSID":"SWS1day","capabilities":"[ESS]","timestamp":13450488710,"level":-64,"frequency":2462},"00:24:14:ff:f4:b4":{"SSID":"Wi2","capabilities":"[ESS]","timestamp":13450488552,"level":-60,"frequency":2462},"2c:36:f8:0e:6b:20":{"SSID":"eng.ut","capabilities":"[WPA2-PSK-CCMP][ESS]","timestamp":13450488846,"level":-56,"frequency":2437},"2c:36:f8:0f:ff:a0":{"SSID":"eng.ut","capabilities":"[WPA2-PSK-CCMP][ESS]","timestamp":13462354733,"level":-37,"frequency":2462},"2c:36:f8:0f:ff:a4":{"SSID":"bld2-guest","capabilities":"[WEP][ESS]","timestamp":13462354753,"level":-37,"frequency":2462},"2c:36:f8:0f:ff:a3":{"SSID":"utroam-1x","capabilities":"[WPA2-EAP-CCMP][ESS]","timestamp":13462354836,"level":-39,"frequency":2462},"2c:36:f8:0f:ff:a2":{"SSID":"utroam","capabilities":"[WPA-PSK-CCMP][WPA2-PSK-CCMP][ESS]","timestamp":13462354766,"level":-38,"frequency":2462},"2c:36:f8:0f:ff:a8":{"SSID":"eng.ut-guest","capabilities":"[ESS]","timestamp":13462354740,"level":-38,"frequency":2462},"2c:36:f8:0f:ff:a7":{"SSID":"ist_members","capabilities":"[WPA2-PSK-CCMP][ESS]","timestamp":13462354830,"level":-38,"frequency":2462},"2c:36:f8:0f:ff:a6":{"SSID":"sanshiro","capabilities":"[WPA2-PSK-CCMP][ESS]","timestamp":13462354780,"level":-37,"frequency":2462},"2c:36:f8:0f:ff:a5":{"SSID":"eng.ut-1x","capabilities":"[WPA2-EAP-CCMP][ESS]","timestamp":13462354848,"level":-37,"frequency":2462},"10:c6:1f:eb:a8:8e":{"SSID":"GL01P-10C61FEBA88E","capabilities":"[WPA-PSK-TKIP][WPA2-PSK-CCMP+TKIP][WPS][ESS]","timestamp":13462354798,"level":-68,"frequency":2422},"2c:36:f8:60:23:50":{"SSID":"eng.ut","capabilities":"[WPA2-PSK-CCMP][ESS]","timestamp":13462354818,"level":-64,"frequency":2462},"2c:36:f8:60:23:56":{"SSID":"sanshiro","capabilities":"[WPA2-PSK-CCMP][ESS]","timestamp":13462354842,"level":-63,"frequency":2462},"2c:36:f8:60:23:57":{"SSID":"ist_members","capabilities":"[WPA2-PSK-CCMP][ESS]","timestamp":13462354700,"level":-59,"frequency":2462},"2c:36:f8:60:23:58":{"SSID":"eng.ut-guest","capabilities":"[ESS]","timestamp":13462354823,"level":-63,"frequency":2462},"2c:36:f8:60:23:52":{"SSID":"utroam","capabilities":"[WPA-PSK-CCMP][WPA2-PSK-CCMP][ESS]","timestamp":13462354871,"level":-66,"frequency":2462},"2c:36:f8:60:23:53":{"SSID":"utroam-1x","capabilities":"[WPA2-EAP-CCMP][ESS]","timestamp":13462354746,"level":-61,"frequency":2462},"2c:36:f8:60:23:54":{"SSID":"bld2-guest","capabilities":"[WEP][ESS]","timestamp":13462354791,"level":-62,"frequency":2462},"2c:36:f8:60:23:55":{"SSID":"eng.ut-1x","capabilities":"[WPA2-EAP-CCMP][ESS]","timestamp":13462354760,"level":-61,"frequency":2462},"2c:36:f8:0f:64:38":{"SSID":"eng.ut-guest","capabilities":"[ESS]","timestamp":13462354707,"level":-64,"frequency":2412},"2c:36:f8:60:0f:70":{"SSID":"eng.ut","capabilities":"[WPA2-PSK-CCMP][ESS]","timestamp":13450488453,"level":-56,"frequency":2412},"00:24:14:ff:f4:b7":{"SSID":"0000docomo","capabilities":"[WPA2-PSK-CCMP][ESS]","timestamp":13450489082,"level":-63,"frequency":2462},"2c:36:f8:0f:64:32":{"SSID":"utroam","capabilities":"[WPA-PSK-CCMP][WPA2-PSK-CCMP][ESS]","timestamp":13462354714,"level":-64,"frequency":2412},"2c:36:f8:0f:d3:20":{"SSID":"eng.ut","capabilities":"[WPA2-PSK-CCMP][ESS]","timestamp":13450488919,"level":-80,"frequency":2437},"2c:36:f8:60:0f:74":{"SSID":"bld2-guest","capabilities":"[WEP][ESS]","timestamp":13450488469,"level":-59,"frequency":2412},"2c:36:f8:60:0f:72":{"SSID":"utroam","capabilities":"[WPA-PSK-CCMP][WPA2-PSK-CCMP][ESS]","timestamp":13450488486,"level":-59,"frequency":2412},"2c:36:f8:0f:64:30":{"SSID":"eng.ut","capabilities":"[WPA2-PSK-CCMP][ESS]","timestamp":13462354726,"level":-63,"frequency":2412}},"magnetic":{"x":-9.133117,"y":8.332826,"z":43.672253},"gravity":{"x":-0.5247791,"y":6.9723644,"z":6.8759975}},"location":{"floor":"3F","accuracy":0.5,"latitude":35.714478081351935,"longitude":139.76190235465765}}]