[{"fingerprint":{"pressure":1019.51965,"wifi":{"2c:36:f8:0f:d2:c4":{"SSID":"bld2-guest","capabilities":"[WEP][ESS]","timestamp":912780879238,"level":-57,"frequency":2437},"00:24:a5:c0:6a:c5":{"SSID":"0024A5C06AC4_A","capabilities":"[WPA-PSK-CCMP+TKIP][WPA2-PSK-CCMP+TKIP][WPS][ESS]","timestamp":912780879297,"level":-77,"frequency":5240},"2c:36:f8:0f:d2:c3":{"SSID":"utroam-1x","capabilities":"[WPA2-EAP-CCMP][ESS]","timestamp":912780879224,"level":-58,"frequency":2437},"2c:36:f8:0f:fb:c0":{"SSID":"eng.ut","capabilities":"[WPA2-PSK-CCMP][ESS]","timestamp":912780879226,"level":-51,"frequency":2412},"2c:36:f8:0f:d2:c2":{"SSID":"utroam","capabilities":"[WPA-PSK-CCMP][WPA2-PSK-CCMP][ESS]","timestamp":912780879229,"level":-58,"frequency":2437},"2e:b1:7f:e0:c7:ea":{"SSID":"","capabilities":"[WEP][ESS]","timestamp":912780879254,"level":-68,"frequency":2462},"00:24:a5:ea:54:72":{"SSID":"0024A5EA5472_G","capabilities":"[WPA2-PSK-CCMP][ESS]","timestamp":912780879220,"level":-81,"frequency":2412},"2c:36:f8:0f:d2:c8":{"SSID":"eng.ut-guest","capabilities":"[ESS]","timestamp":912780879235,"level":-57,"frequency":2437},"2c:36:f8:0f:fb:c4":{"SSID":"bld2-guest","capabilities":"[WEP][ESS]","timestamp":912780879215,"level":-51,"frequency":2412},"00:24:a5:ea:54:73":{"SSID":"0024A5EA5472_A","capabilities":"[WPA-PSK-CCMP][ESS]","timestamp":912780879288,"level":-81,"frequency":5200},"2c:36:f8:0f:d2:c7":{"SSID":"eng.ut-guest","capabilities":"[ESS]","timestamp":912780879309,"level":-64,"frequency":5240},"00:24:a5:c0:6a:c4":{"SSID":"0024A5C06AC4_G","capabilities":"[WPA-PSK-CCMP+TKIP][WPA2-PSK-CCMP+TKIP][WPS][ESS]","timestamp":912765719799,"level":-76,"frequency":2412},"2c:36:f8:0f:d2:c6":{"SSID":"sanshiro","capabilities":"[WPA2-PSK-CCMP][ESS]","timestamp":912780879233,"level":-57,"frequency":2437},"2c:36:f8:0f:fb:c6":{"SSID":"sanshiro","capabilities":"[WPA2-PSK-CCMP][ESS]","timestamp":912765719812,"level":-46,"frequency":2412},"2c:36:f8:0f:fb:c7":{"SSID":"eng.ut-guest","capabilities":"[ESS]","timestamp":912780879276,"level":-45,"frequency":5200},"2c:36:f8:0f:fb:c8":{"SSID":"eng.ut-guest","capabilities":"[ESS]","timestamp":912765719810,"level":-45,"frequency":2412},"2c:36:f8:0f:fb:c9":{"SSID":"sanshiro","capabilities":"[WPA2-PSK-CCMP][ESS]","timestamp":912780879279,"level":-45,"frequency":5200},"2c:36:f8:0f:d2:c9":{"SSID":"sanshiro","capabilities":"[WPA2-PSK-CCMP][ESS]","timestamp":912780879302,"level":-64,"frequency":5240},"2c:36:f8:60:01:1f":{"SSID":"eng.ut","capabilities":"[WPA2-PSK-CCMP][ESS]","timestamp":912780879261,"level":-62,"frequency":5180},"2c:36:f8:60:01:1b":{"SSID":"bld2-guest","capabilities":"[WEP][ESS]","timestamp":912780879265,"level":-62,"frequency":5180},"2c:36:f8:0f:d2:c0":{"SSID":"eng.ut","capabilities":"[WPA2-PSK-CCMP][ESS]","timestamp":912780879231,"level":-57,"frequency":2437},"b0:c7:45:97:87:00":{"SSID":"sl-intra-c-g","capabilities":"[WPA2-PSK-CCMP][WPS][ESS]","timestamp":912765719814,"level":-64,"frequency":2417},"2c:36:f8:60:01:1d":{"SSID":"utroam","capabilities":"[WPA-PSK-CCMP][WPA2-PSK-CCMP][ESS]","timestamp":912780879267,"level":-62,"frequency":5180},"b0:c7:45:32:02:60":{"SSID":"HRD0-G","capabilities":"[WPA2-PSK-CCMP][WPS][ESS]","timestamp":912780879222,"level":-79,"frequency":2427},"06:24:a5:c0:6a:c4":{"SSID":"0024A5C06AC4_G-1","capabilities":"[WPA-PSK-CCMP][ESS]","timestamp":912765719808,"level":-77,"frequency":2412},"06:24:a5:c0:6a:c5":{"SSID":"0024A5C06AC4_A-1","capabilities":"[WPA-PSK-CCMP][ESS]","timestamp":912780879299,"level":-77,"frequency":5240},"00:00:00:00:00:00":{"SSID":"","capabilities":"[ESS]","timestamp":359168172488,"level":-87,"frequency":5280},"00:24:a5:e9:bc:db":{"SSID":"grits59ilex2","capabilities":"[WPA-PSK-CCMP+TKIP][WPA2-PSK-CCMP+TKIP][WPS][ESS]","timestamp":912780879319,"level":-70,"frequency":5660},"00:24:a5:e9:bc:da":{"SSID":"grits59ilex2g","capabilities":"[WPA-PSK-CCMP+TKIP][WPA2-PSK-CCMP+TKIP][WPS][ESS]","timestamp":912780879218,"level":-74,"frequency":2412},"2c:36:f8:60:01:14":{"SSID":"bld2-guest","capabilities":"[WEP][ESS]","timestamp":912780879249,"level":-56,"frequency":2462},"2c:36:f8:60:01:13":{"SSID":"utroam-1x","capabilities":"[WPA2-EAP-CCMP][ESS]","timestamp":912780879258,"level":-59,"frequency":2462},"70:73:cb:b9:73:58":{"SSID":"","capabilities":"[WPA2-PSK-CCMP][ESS]","timestamp":912765719912,"level":-75,"frequency":5540},"2c:36:f8:60:01:12":{"SSID":"utroam","capabilities":"[WPA-PSK-CCMP][WPA2-PSK-CCMP][ESS]","timestamp":912780879251,"level":-56,"frequency":2462},"2c:36:f8:0f:d2:cf":{"SSID":"eng.ut","capabilities":"[WPA2-PSK-CCMP][ESS]","timestamp":912780879292,"level":-64,"frequency":5240},"1c:b1:7f:e0:c7:eb":{"SSID":"sl-intra-d-a","capabilities":"[WPA2-PSK-CCMP][WPS][ESS]","timestamp":912780879306,"level":-60,"frequency":5240},"1c:b1:7f:e0:c7:ea":{"SSID":"sl-intra-d-g","capabilities":"[WPA2-PSK-CCMP][WPS][ESS]","timestamp":912780879245,"level":-69,"frequency":2462},"2c:36:f8:60:01:10":{"SSID":"eng.ut","capabilities":"[WPA2-PSK-CCMP][ESS]","timestamp":912765719840,"level":-58,"frequency":2462},"2c:36:f8:0f:d2:cd":{"SSID":"utroam","capabilities":"[WPA-PSK-CCMP][WPA2-PSK-CCMP][ESS]","timestamp":912780879313,"level":-64,"frequency":5240},"2c:36:f8:0f:d2:cb":{"SSID":"bld2-guest","capabilities":"[WEP][ESS]","timestamp":912780879311,"level":-64,"frequency":5240},"2c:36:f8:60:01:19":{"SSID":"sanshiro","capabilities":"[WPA2-PSK-CCMP][ESS]","timestamp":912780879270,"level":-62,"frequency":5180},"2c:36:f8:60:01:18":{"SSID":"eng.ut-guest","capabilities":"[ESS]","timestamp":912780879247,"level":-56,"frequency":2462},"2c:36:f8:60:01:17":{"SSID":"ist_members","capabilities":"[WPA2-PSK-CCMP][ESS]","timestamp":912780879256,"level":-58,"frequency":2462},"2c:36:f8:60:01:16":{"SSID":"sanshiro","capabilities":"[WPA2-PSK-CCMP][ESS]","timestamp":912765719838,"level":-58,"frequency":2462},"00:3a:9d:f4:49:3f":{"SSID":"","capabilities":"[WPA2-PSK-CCMP][ESS]","timestamp":912765719865,"level":-86,"frequency":5180},"2c:36:f8:0f:fb:cc":{"SSID":"utroam-1x","capabilities":"[WPA2-EAP-CCMP][ESS]","timestamp":912765719883,"level":-47,"frequency":5200},"2c:36:f8:0f:fb:cd":{"SSID":"utroam","capabilities":"[WPA-PSK-CCMP][WPA2-PSK-CCMP][ESS]","timestamp":912780879283,"level":-45,"frequency":5200},"2c:36:f8:0f:fb:cf":{"SSID":"eng.ut","capabilities":"[WPA2-PSK-CCMP][ESS]","timestamp":912780879274,"level":-45,"frequency":5200},"2c:36:f8:0f:fb:cb":{"SSID":"bld2-guest","capabilities":"[WEP][ESS]","timestamp":912780879281,"level":-45,"frequency":5200},"b0:c7:45:97:87:10":{"SSID":"sl-intra-c-a","capabilities":"[WPA2-PSK-CCMP][WPS][ESS]","timestamp":912780879316,"level":-67,"frequency":5300},"1c:b1:7f:e2:55:d3":{"SSID":"aterm-34407b-a","capabilities":"[WPA-PSK-CCMP][WPA2-PSK-CCMP][WPS][ESS]","timestamp":912780879294,"level":-59,"frequency":5240},"1c:b1:7f:e2:55:d2":{"SSID":"aterm-34407b-g","capabilities":"[WPA-PSK-CCMP][WPA2-PSK-CCMP][WPS][ESS]","timestamp":912780879242,"level":-72,"frequency":2452}},"magnetic":{"x":77.37274,"y":-48.5672,"z":-13.40332},"gravity":{"x":8.336082,"y":5.1650996,"z":-0.043217868}},"location":{"floor":"8F","accuracy":0.5,"latitude":35.71409424631808,"longitude":139.76167604327202}},{"fingerprint":{"pressure":1019.52966,"wifi":{"2c:36:f8:0f:d2:c4":{"SSID":"bld2-guest","capabilities":"[WEP][ESS]","timestamp":912793983815,"level":-53,"frequency":2437},"00:24:a5:c0:6a:c5":{"SSID":"0024A5C06AC4_A","capabilities":"[WPA-PSK-CCMP+TKIP][WPA2-PSK-CCMP+TKIP][WPS][ESS]","timestamp":912793983873,"level":-78,"frequency":5240},"2c:36:f8:0f:d2:c3":{"SSID":"utroam-1x","capabilities":"[WPA2-EAP-CCMP][ESS]","timestamp":912793983811,"level":-54,"frequency":2437},"2c:36:f8:0f:fb:c0":{"SSID":"eng.ut","capabilities":"[WPA2-PSK-CCMP][ESS]","timestamp":912793983787,"level":-53,"frequency":2412},"2c:36:f8:0f:d2:c2":{"SSID":"utroam","capabilities":"[WPA-PSK-CCMP][WPA2-PSK-CCMP][ESS]","timestamp":912780879229,"level":-58,"frequency":2437},"2c:36:f8:0f:fb:c2":{"SSID":"utroam","capabilities":"[WPA-PSK-CCMP][WPA2-PSK-CCMP][ESS]","timestamp":912793983795,"level":-71,"frequency":2412},"2e:b1:7f:e0:c7:ea":{"SSID":"","capabilities":"[WEP][ESS]","timestamp":912780879254,"level":-68,"frequency":2462},"00:24:a5:ea:54:72":{"SSID":"0024A5EA5472_G","capabilities":"[WPA2-PSK-CCMP][ESS]","timestamp":912793983791,"level":-78,"frequency":2412},"2c:36:f8:0f:d2:c8":{"SSID":"eng.ut-guest","capabilities":"[ESS]","timestamp":912793983813,"level":-54,"frequency":2437},"2c:36:f8:0f:fb:c4":{"SSID":"bld2-guest","capabilities":"[WEP][ESS]","timestamp":912780879215,"level":-51,"frequency":2412},"00:24:a5:ea:54:73":{"SSID":"0024A5EA5472_A","capabilities":"[WPA-PSK-CCMP][ESS]","timestamp":912793983850,"level":-87,"frequency":5200},"2c:36:f8:0f:d2:c7":{"SSID":"eng.ut-guest","capabilities":"[ESS]","timestamp":912793983878,"level":-64,"frequency":5240},"2c:36:f8:0f:d2:c6":{"SSID":"sanshiro","capabilities":"[WPA2-PSK-CCMP][ESS]","timestamp":912780879233,"level":-57,"frequency":2437},"2c:36:f8:0f:d2:c5":{"SSID":"eng.ut-1x","capabilities":"[WPA2-EAP-CCMP][ESS]","timestamp":912793983804,"level":-79,"frequency":2437},"2c:36:f8:0f:fb:c6":{"SSID":"sanshiro","capabilities":"[WPA2-PSK-CCMP][ESS]","timestamp":912793983798,"level":-62,"frequency":2412},"2c:36:f8:0f:fb:c7":{"SSID":"eng.ut-guest","capabilities":"[ESS]","timestamp":912793983852,"level":-52,"frequency":5200},"2c:36:f8:0f:fb:c8":{"SSID":"eng.ut-guest","capabilities":"[ESS]","timestamp":912793983789,"level":-52,"frequency":2412},"2c:36:f8:0f:fb:c9":{"SSID":"sanshiro","capabilities":"[WPA2-PSK-CCMP][ESS]","timestamp":912793983859,"level":-52,"frequency":5200},"2c:36:f8:0f:d2:c9":{"SSID":"sanshiro","capabilities":"[WPA2-PSK-CCMP][ESS]","timestamp":912793983885,"level":-64,"frequency":5240},"2c:36:f8:60:01:1f":{"SSID":"eng.ut","capabilities":"[WPA2-PSK-CCMP][ESS]","timestamp":912793983834,"level":-65,"frequency":5180},"2c:36:f8:60:01:1b":{"SSID":"bld2-guest","capabilities":"[WEP][ESS]","timestamp":912793983838,"level":-65,"frequency":5180},"2c:36:f8:0f:d2:c0":{"SSID":"eng.ut","capabilities":"[WPA2-PSK-CCMP][ESS]","timestamp":912793983809,"level":-54,"frequency":2437},"2c:36:f8:60:01:1d":{"SSID":"utroam","capabilities":"[WPA-PSK-CCMP][WPA2-PSK-CCMP][ESS]","timestamp":912793983841,"level":-65,"frequency":5180},"b0:c7:45:32:02:60":{"SSID":"HRD0-G","capabilities":"[WPA2-PSK-CCMP][WPS][ESS]","timestamp":912793983802,"level":-70,"frequency":2427},"b0:c7:45:32:02:65":{"SSID":"HRD0-A","capabilities":"[WPA2-PSK-CCMP][WPS][ESS]","timestamp":912793983892,"level":-74,"frequency":5620},"1c:b1:7f:a5:16:9a":{"SSID":"","capabilities":"[WPA2-PSK-CCMP][WPS][ESS]","timestamp":912793983831,"level":-77,"frequency":2462},"06:24:a5:c0:6a:c4":{"SSID":"0024A5C06AC4_G-1","capabilities":"[WPA-PSK-CCMP][ESS]","timestamp":912793983793,"level":-72,"frequency":2412},"06:24:a5:c0:6a:c5":{"SSID":"0024A5C06AC4_A-1","capabilities":"[WPA-PSK-CCMP][ESS]","timestamp":912793983875,"level":-78,"frequency":5240},"00:00:00:00:00:00":{"SSID":"","capabilities":"[ESS]","timestamp":359168172488,"level":-87,"frequency":5280},"00:24:a5:e9:bc:db":{"SSID":"grits59ilex2","capabilities":"[WPA-PSK-CCMP+TKIP][WPA2-PSK-CCMP+TKIP][WPS][ESS]","timestamp":912793983895,"level":-73,"frequency":5660},"00:24:a5:e9:bc:da":{"SSID":"grits59ilex2g","capabilities":"[WPA-PSK-CCMP+TKIP][WPA2-PSK-CCMP+TKIP][WPS][ESS]","timestamp":912793983784,"level":-64,"frequency":2412},"2c:36:f8:60:01:14":{"SSID":"bld2-guest","capabilities":"[WEP][ESS]","timestamp":912793983827,"level":-50,"frequency":2462},"2c:36:f8:60:01:13":{"SSID":"utroam-1x","capabilities":"[WPA2-EAP-CCMP][ESS]","timestamp":912780879258,"level":-59,"frequency":2462},"2c:36:f8:60:01:12":{"SSID":"utroam","capabilities":"[WPA-PSK-CCMP][WPA2-PSK-CCMP][ESS]","timestamp":912793983829,"level":-50,"frequency":2462},"2c:36:f8:0f:d2:cf":{"SSID":"eng.ut","capabilities":"[WPA2-PSK-CCMP][ESS]","timestamp":912793983866,"level":-64,"frequency":5240},"1c:b1:7f:e0:c7:eb":{"SSID":"sl-intra-d-a","capabilities":"[WPA2-PSK-CCMP][WPS][ESS]","timestamp":912793983868,"level":-58,"frequency":5240},"1c:b1:7f:e0:c7:ea":{"SSID":"sl-intra-d-g","capabilities":"[WPA2-PSK-CCMP][WPS][ESS]","timestamp":912793983820,"level":-68,"frequency":2462},"2c:36:f8:60:01:10":{"SSID":"eng.ut","capabilities":"[WPA2-PSK-CCMP][ESS]","timestamp":912793983825,"level":-51,"frequency":2462},"2c:36:f8:0f:d2:cd":{"SSID":"utroam","capabilities":"[WPA-PSK-CCMP][WPA2-PSK-CCMP][ESS]","timestamp":912793983882,"level":-64,"frequency":5240},"2c:36:f8:0f:d2:cb":{"SSID":"bld2-guest","capabilities":"[WEP][ESS]","timestamp":912793983880,"level":-64,"frequency":5240},"2c:36:f8:60:01:19":{"SSID":"sanshiro","capabilities":"[WPA2-PSK-CCMP][ESS]","timestamp":912793983843,"level":-65,"frequency":5180},"2c:36:f8:60:01:18":{"SSID":"eng.ut-guest","capabilities":"[ESS]","timestamp":912793983822,"level":-51,"frequency":2462},"2c:36:f8:60:01:17":{"SSID":"ist_members","capabilities":"[WPA2-PSK-CCMP][ESS]","timestamp":912780879256,"level":-58,"frequency":2462},"2c:36:f8:0f:fb:cd":{"SSID":"utroam","capabilities":"[WPA-PSK-CCMP][WPA2-PSK-CCMP][ESS]","timestamp":912793983857,"level":-52,"frequency":5200},"2c:36:f8:0f:fb:cf":{"SSID":"eng.ut","capabilities":"[WPA2-PSK-CCMP][ESS]","timestamp":912793983847,"level":-53,"frequency":5200},"2c:36:f8:0f:fb:ca":{"SSID":"eng.ut-1x","capabilities":"[WPA2-EAP-CCMP][ESS]","timestamp":912793983863,"level":-53,"frequency":5200},"2c:36:f8:0f:fb:cb":{"SSID":"bld2-guest","capabilities":"[WEP][ESS]","timestamp":912793983854,"level":-52,"frequency":5200},"b0:c7:45:97:87:10":{"SSID":"sl-intra-c-a","capabilities":"[WPA2-PSK-CCMP][WPS][ESS]","timestamp":912793983890,"level":-74,"frequency":5300},"1c:b1:7f:e2:55:d3":{"SSID":"aterm-34407b-a","capabilities":"[WPA-PSK-CCMP][WPA2-PSK-CCMP][WPS][ESS]","timestamp":912793983871,"level":-49,"frequency":5240},"1c:b1:7f:e2:55:d2":{"SSID":"aterm-34407b-g","capabilities":"[WPA-PSK-CCMP][WPA2-PSK-CCMP][WPS][ESS]","timestamp":912793983817,"level":-62,"frequency":2452}},"magnetic":{"x":-33.355713,"y":-36.62262,"z":65.05585},"gravity":{"x":9.805946,"y":-0.027910024,"z":-0.114165016}},"location":{"floor":"8F","accuracy":0.5,"latitude":35.71406838502591,"longitude":139.7615848481655}},{"fingerprint":{"pressure":1019.6096,"wifi":{"2c:36:f8:0f:d2:c4":{"SSID":"bld2-guest","capabilities":"[WEP][ESS]","timestamp":912793983815,"level":-53,"frequency":2437},"00:16:01:c9:fe:8a":{"SSID":"ISIWireless2","capabilities":"[WPS][WEP][ESS]","timestamp":912841345420,"level":-87,"frequency":5240},"00:24:a5:c0:6a:c5":{"SSID":"0024A5C06AC4_A","capabilities":"[WPA-PSK-CCMP+TKIP][WPA2-PSK-CCMP+TKIP][WPS][ESS]","timestamp":912793983873,"level":-78,"frequency":5240},"2c:36:f8:0f:d2:c3":{"SSID":"utroam-1x","capabilities":"[WPA2-EAP-CCMP][ESS]","timestamp":912793983811,"level":-54,"frequency":2437},"2c:36:f8:0f:fb:c0":{"SSID":"eng.ut","capabilities":"[WPA2-PSK-CCMP][ESS]","timestamp":912793983787,"level":-53,"frequency":2412},"2c:36:f8:0f:fb:c2":{"SSID":"utroam","capabilities":"[WPA-PSK-CCMP][WPA2-PSK-CCMP][ESS]","timestamp":912793983795,"level":-71,"frequency":2412},"00:24:a5:ea:54:72":{"SSID":"0024A5EA5472_G","capabilities":"[WPA2-PSK-CCMP][ESS]","timestamp":912793983791,"level":-78,"frequency":2412},"2c:36:f8:0f:d2:c8":{"SSID":"eng.ut-guest","capabilities":"[ESS]","timestamp":912793983813,"level":-54,"frequency":2437},"00:24:a5:ea:54:73":{"SSID":"0024A5EA5472_A","capabilities":"[WPA-PSK-CCMP][ESS]","timestamp":912793983850,"level":-87,"frequency":5200},"2c:36:f8:0f:d2:c7":{"SSID":"eng.ut-guest","capabilities":"[ESS]","timestamp":912793983878,"level":-64,"frequency":5240},"2c:36:f8:0f:d2:c5":{"SSID":"eng.ut-1x","capabilities":"[WPA2-EAP-CCMP][ESS]","timestamp":912793983804,"level":-79,"frequency":2437},"2c:36:f8:0f:fb:c6":{"SSID":"sanshiro","capabilities":"[WPA2-PSK-CCMP][ESS]","timestamp":912793983798,"level":-62,"frequency":2412},"2c:36:f8:0f:fd:2f":{"SSID":"eng.ut","capabilities":"[WPA2-PSK-CCMP][ESS]","timestamp":912841345369,"level":-50,"frequency":5220},"2c:36:f8:0f:fb:c7":{"SSID":"eng.ut-guest","capabilities":"[ESS]","timestamp":912793983852,"level":-52,"frequency":5200},"2c:36:f8:0f:fb:c8":{"SSID":"eng.ut-guest","capabilities":"[ESS]","timestamp":912793983789,"level":-52,"frequency":2412},"2c:36:f8:0f:fd:2d":{"SSID":"utroam","capabilities":"[WPA-PSK-CCMP][WPA2-PSK-CCMP][ESS]","timestamp":912841345381,"level":-50,"frequency":5220},"2c:36:f8:0f:fb:c9":{"SSID":"sanshiro","capabilities":"[WPA2-PSK-CCMP][ESS]","timestamp":912793983859,"level":-52,"frequency":5200},"2c:36:f8:0f:d2:c9":{"SSID":"sanshiro","capabilities":"[WPA2-PSK-CCMP][ESS]","timestamp":912793983885,"level":-64,"frequency":5240},"2c:36:f8:0f:fd:2b":{"SSID":"bld2-guest","capabilities":"[WEP][ESS]","timestamp":912841345377,"level":-50,"frequency":5220},"2c:36:f8:60:01:1f":{"SSID":"eng.ut","capabilities":"[WPA2-PSK-CCMP][ESS]","timestamp":912793983834,"level":-65,"frequency":5180},"2c:36:f8:60:08:09":{"SSID":"sanshiro","capabilities":"[WPA2-PSK-CCMP][ESS]","timestamp":912841345396,"level":-86,"frequency":5220},"2c:36:f8:0f:fb:7b":{"SSID":"bld2-guest","capabilities":"[WEP][ESS]","timestamp":912841345408,"level":-62,"frequency":5240},"10:6f:3f:ab:2c:90":{"SSID":"","capabilities":"[WPA2-PSK-CCMP][WPS][ESS]","timestamp":912841345273,"level":-75,"frequency":2462},"2c:36:f8:60:01:1b":{"SSID":"bld2-guest","capabilities":"[WEP][ESS]","timestamp":912793983838,"level":-65,"frequency":5180},"2c:36:f8:0f:d2:c0":{"SSID":"eng.ut","capabilities":"[WPA2-PSK-CCMP][ESS]","timestamp":912793983809,"level":-54,"frequency":2437},"2c:36:f8:60:01:1d":{"SSID":"utroam","capabilities":"[WPA-PSK-CCMP][WPA2-PSK-CCMP][ESS]","timestamp":912793983841,"level":-65,"frequency":5180},"2c:36:f8:0f:ce:36":{"SSID":"sanshiro","capabilities":"[WPA2-PSK-CCMP][ESS]","timestamp":912841345277,"level":-63,"frequency":2462},"b0:c7:45:32:02:60":{"SSID":"HRD0-G","capabilities":"[WPA2-PSK-CCMP][WPS][ESS]","timestamp":912793983802,"level":-70,"frequency":2427},"2c:36:f8:0f:ce:38":{"SSID":"eng.ut-guest","capabilities":"[ESS]","timestamp":912841345280,"level":-64,"frequency":2462},"2c:36:f8:0f:ce:37":{"SSID":"eng.ut-guest","capabilities":"[ESS]","timestamp":912841345296,"level":-72,"frequency":5180},"2c:36:f8:0f:ce:39":{"SSID":"sanshiro","capabilities":"[WPA2-PSK-CCMP][ESS]","timestamp":912841345361,"level":-72,"frequency":5180},"2c:36:f8:0f:fb:70":{"SSID":"eng.ut","capabilities":"[WPA2-PSK-CCMP][ESS]","timestamp":912841345243,"level":-83,"frequency":2437},"b0:c7:45:32:02:65":{"SSID":"HRD0-A","capabilities":"[WPA2-PSK-CCMP][WPS][ESS]","timestamp":912793983892,"level":-74,"frequency":5620},"1c:b1:7f:a5:16:9a":{"SSID":"","capabilities":"[WPA2-PSK-CCMP][WPS][ESS]","timestamp":912793983831,"level":-77,"frequency":2462},"2c:36:f8:0f:fb:79":{"SSID":"sanshiro","capabilities":"[WPA2-PSK-CCMP][ESS]","timestamp":912841345416,"level":-62,"frequency":5240},"2c:36:f8:0f:fb:77":{"SSID":"eng.ut-guest","capabilities":"[ESS]","timestamp":912841345404,"level":-62,"frequency":5240},"2c:36:f8:0f:fb:78":{"SSID":"eng.ut-guest","capabilities":"[ESS]","timestamp":912841345247,"level":-51,"frequency":2437},"2c:36:f8:0f:fb:76":{"SSID":"sanshiro","capabilities":"[WPA2-PSK-CCMP][ESS]","timestamp":912841345240,"level":-51,"frequency":2437},"2c:36:f8:0f:fb:74":{"SSID":"bld2-guest","capabilities":"[WEP][ESS]","timestamp":912841345250,"level":-51,"frequency":2437},"2c:36:f8:0f:ce:30":{"SSID":"eng.ut","capabilities":"[WPA2-PSK-CCMP][ESS]","timestamp":912841345258,"level":-63,"frequency":2462},"06:24:a5:c0:6a:c4":{"SSID":"0024A5C06AC4_G-1","capabilities":"[WPA-PSK-CCMP][ESS]","timestamp":912793983793,"level":-72,"frequency":2412},"2c:36:f8:0f:ce:32":{"SSID":"utroam","capabilities":"[WPA-PSK-CCMP][WPA2-PSK-CCMP][ESS]","timestamp":912841345269,"level":-63,"frequency":2462},"2c:36:f8:0f:ce:33":{"SSID":"utroam-1x","capabilities":"[WPA2-EAP-CCMP][ESS]","timestamp":912841345262,"level":-62,"frequency":2462},"06:24:a5:c0:6a:c5":{"SSID":"0024A5C06AC4_A-1","capabilities":"[WPA-PSK-CCMP][ESS]","timestamp":912793983875,"level":-78,"frequency":5240},"00:00:00:00:00:00":{"SSID":"","capabilities":"[ESS]","timestamp":359168172488,"level":-87,"frequency":5280},"2c:36:f8:60:08:0d":{"SSID":"utroam","capabilities":"[WPA-PSK-CCMP][WPA2-PSK-CCMP][ESS]","timestamp":912841345392,"level":-86,"frequency":5220},"2c:36:f8:0f:ce:3d":{"SSID":"utroam","capabilities":"[WPA-PSK-CCMP][WPA2-PSK-CCMP][ESS]","timestamp":912841345288,"level":-71,"frequency":5180},"2c:36:f8:0f:ce:3b":{"SSID":"bld2-guest","capabilities":"[WEP][ESS]","timestamp":912841345357,"level":-72,"frequency":5180},"00:24:a5:e9:bc:db":{"SSID":"grits59ilex2","capabilities":"[WPA-PSK-CCMP+TKIP][WPA2-PSK-CCMP+TKIP][WPS][ESS]","timestamp":912793983895,"level":-73,"frequency":5660},"00:24:a5:e9:bc:da":{"SSID":"grits59ilex2g","capabilities":"[WPA-PSK-CCMP+TKIP][WPA2-PSK-CCMP+TKIP][WPS][ESS]","timestamp":912793983784,"level":-64,"frequency":2412},"2c:36:f8:60:01:14":{"SSID":"bld2-guest","capabilities":"[WEP][ESS]","timestamp":912793983827,"level":-50,"frequency":2462},"2c:36:f8:0f:fd:29":{"SSID":"sanshiro","capabilities":"[WPA2-PSK-CCMP][ESS]","timestamp":912841345385,"level":-50,"frequency":5220},"2c:36:f8:0f:fd:28":{"SSID":"ist_members","capabilities":"[WPA2-PSK-CCMP][ESS]","timestamp":912841345388,"level":-50,"frequency":5220},"2c:36:f8:60:01:12":{"SSID":"utroam","capabilities":"[WPA-PSK-CCMP][WPA2-PSK-CCMP][ESS]","timestamp":912793983829,"level":-50,"frequency":2462},"2c:36:f8:0f:d2:cf":{"SSID":"eng.ut","capabilities":"[WPA2-PSK-CCMP][ESS]","timestamp":912793983866,"level":-64,"frequency":5240},"1c:b1:7f:e0:c7:eb":{"SSID":"sl-intra-d-a","capabilities":"[WPA2-PSK-CCMP][WPS][ESS]","timestamp":912793983868,"level":-58,"frequency":5240},"1c:b1:7f:e0:c7:ea":{"SSID":"sl-intra-d-g","capabilities":"[WPA2-PSK-CCMP][WPS][ESS]","timestamp":912793983820,"level":-68,"frequency":2462},"2c:36:f8:60:01:10":{"SSID":"eng.ut","capabilities":"[WPA2-PSK-CCMP][ESS]","timestamp":912793983825,"level":-51,"frequency":2462},"2c:36:f8:0f:d2:cd":{"SSID":"utroam","capabilities":"[WPA-PSK-CCMP][WPA2-PSK-CCMP][ESS]","timestamp":912793983882,"level":-64,"frequency":5240},"2c:36:f8:0f:d2:cb":{"SSID":"bld2-guest","capabilities":"[WEP][ESS]","timestamp":912793983880,"level":-64,"frequency":5240},"2c:36:f8:0f:fd:23":{"SSID":"utroam-1x","capabilities":"[WPA2-EAP-CCMP][ESS]","timestamp":912841345232,"level":-51,"frequency":2412},"2c:36:f8:0f:fd:20":{"SSID":"eng.ut","capabilities":"[WPA2-PSK-CCMP][ESS]","timestamp":912841345224,"level":-51,"frequency":2412},"2c:36:f8:0f:fd:27":{"SSID":"eng.ut-guest","capabilities":"[ESS]","timestamp":912841345373,"level":-50,"frequency":5220},"2c:36:f8:60:01:19":{"SSID":"sanshiro","capabilities":"[WPA2-PSK-CCMP][ESS]","timestamp":912793983843,"level":-65,"frequency":5180},"2c:36:f8:60:01:18":{"SSID":"eng.ut-guest","capabilities":"[ESS]","timestamp":912793983822,"level":-51,"frequency":2462},"2c:36:f8:60:01:17":{"SSID":"eng.ut-guest","capabilities":"[ESS]","timestamp":912793983836,"level":-65,"frequency":5180},"2c:36:f8:0f:fb:7f":{"SSID":"eng.ut","capabilities":"[WPA2-PSK-CCMP][ESS]","timestamp":912841345400,"level":-62,"frequency":5240},"2c:36:f8:0f:fb:7d":{"SSID":"utroam","capabilities":"[WPA-PSK-CCMP][WPA2-PSK-CCMP][ESS]","timestamp":912841345412,"level":-62,"frequency":5240},"2c:36:f8:0f:fb:7c":{"SSID":"utroam-1x","capabilities":"[WPA2-EAP-CCMP][ESS]","timestamp":912841345424,"level":-62,"frequency":5240},"2c:36:f8:0f:fb:cd":{"SSID":"utroam","capabilities":"[WPA-PSK-CCMP][WPA2-PSK-CCMP][ESS]","timestamp":912793983857,"level":-52,"frequency":5200},"2c:36:f8:0f:fb:cf":{"SSID":"eng.ut","capabilities":"[WPA2-PSK-CCMP][ESS]","timestamp":912793983847,"level":-53,"frequency":5200},"2c:36:f8:0f:fb:ca":{"SSID":"eng.ut-1x","capabilities":"[WPA2-EAP-CCMP][ESS]","timestamp":912793983863,"level":-53,"frequency":5200},"1c:b1:7f:e0:d6:7e":{"SSID":"sl-intra-a-g","capabilities":"[WPA2-PSK-CCMP][WPS][ESS]","timestamp":912841345236,"level":-72,"frequency":2422},"2c:36:f8:0f:fb:cb":{"SSID":"bld2-guest","capabilities":"[WEP][ESS]","timestamp":912793983854,"level":-52,"frequency":5200},"1c:b1:7f:e0:d6:7f":{"SSID":"sl-intra-a-a","capabilities":"[WPA-PSK-CCMP][WPA2-PSK-CCMP][WPS][ESS]","timestamp":912841345292,"level":-66,"frequency":5180},"b0:c7:45:97:87:10":{"SSID":"sl-intra-c-a","capabilities":"[WPA2-PSK-CCMP][WPS][ESS]","timestamp":912793983890,"level":-74,"frequency":5300},"1c:b1:7f:e2:55:d3":{"SSID":"aterm-34407b-a","capabilities":"[WPA-PSK-CCMP][WPA2-PSK-CCMP][WPS][ESS]","timestamp":912793983871,"level":-49,"frequency":5240},"1c:b1:7f:e2:55:d2":{"SSID":"aterm-34407b-g","capabilities":"[WPA-PSK-CCMP][WPA2-PSK-CCMP][WPS][ESS]","timestamp":912793983817,"level":-62,"frequency":2452},"2c:36:f8:0f:ce:3f":{"SSID":"eng.ut","capabilities":"[WPA2-PSK-CCMP][ESS]","timestamp":912841345284,"level":-72,"frequency":5180}},"magnetic":{"x":29.115295,"y":9.008789,"z":-30.343628},"gravity":{"x":9.799497,"y":-0.36861908,"z":-0.06616227}},"location":{"floor":"8F","accuracy":0.5,"latitude":35.714432347913,"longitude":139.76158618927002}}]