[{"fingerprint":{"pressure":1022.4181,"wifi":{"2c:36:f8:60:49:1a":{"SSID":"eng.ut-guest","capabilities":"[ESS]","timestamp":1439663746240,"level":-74,"frequency":5200},"dc:a5:f4:cc:13:fc":{"SSID":"utroam-1x","capabilities":"[WPA2-EAP-CCMP][ESS]","timestamp":1439663746049,"level":-77,"frequency":5180},"dc:a5:f4:cc:13:fd":{"SSID":"utroam","capabilities":"[WPA-PSK-CCMP][WPA2-PSK-CCMP][ESS]","timestamp":1439663746034,"level":-76,"frequency":5180},"00:3a:9d:b8:fc:f1":{"SSID":"ItoLabWireless-A","capabilities":"[WPS][WEP][ESS]","timestamp":1439663746192,"level":-86,"frequency":5180},"2c:36:f8:0f:d3:23":{"SSID":"utroam-1x","capabilities":"[WPA2-EAP-CCMP][ESS]","timestamp":1439689654540,"level":-85,"frequency":2437},"dc:a5:f4:cc:13:fe":{"SSID":"wnet.eng.ut","capabilities":"[WPA2-PSK-TKIP][ESS]","timestamp":1439663746145,"level":-76,"frequency":5180},"2c:36:f8:0f:d3:24":{"SSID":"bld2-guest","capabilities":"[WEP][ESS]","timestamp":1439663745773,"level":-75,"frequency":2437},"dc:a5:f4:cc:13:ff":{"SSID":"eng.ut","capabilities":"[WPA2-PSK-CCMP][ESS]","timestamp":1439663746161,"level":-78,"frequency":5180},"2c:36:f8:0f:d3:25":{"SSID":"eng.ut-1x","capabilities":"[WPA2-EAP-CCMP][ESS]","timestamp":1439663745788,"level":-72,"frequency":2437},"dc:a5:f4:cc:13:fa":{"SSID":"eng.ut-guest","capabilities":"[ESS]","timestamp":1439689654565,"level":-84,"frequency":5180},"b0:c7:45:97:87:00":{"SSID":"sl-intra-c-g","capabilities":"[WPA2-PSK-CCMP][WPS][ESS]","timestamp":1439663745605,"level":-76,"frequency":2422},"2c:36:f8:0f:d3:27":{"SSID":"ist_members","capabilities":"[WPA2-PSK-CCMP][ESS]","timestamp":1439663745699,"level":-75,"frequency":2437},"2c:36:f8:0f:d3:28":{"SSID":"ist_members","capabilities":"[WPA2-PSK-CCMP][ESS]","timestamp":1439689654584,"level":-82,"frequency":5200},"2c:36:f8:0f:fe:bd":{"SSID":"utroam","capabilities":"[WPA-PSK-CCMP][WPA2-PSK-CCMP][ESS]","timestamp":1439663746396,"level":-80,"frequency":5220},"2c:36:f8:0f:fe:bb":{"SSID":"bld2-guest","capabilities":"[WEP][ESS]","timestamp":1439663746381,"level":-81,"frequency":5220},"2c:36:f8:0f:fe:bf":{"SSID":"eng.ut","capabilities":"[WPA2-PSK-CCMP][ESS]","timestamp":1439663746350,"level":-80,"frequency":5220},"dc:a5:f4:cc:13:f5":{"SSID":"eng.ut-guest","capabilities":"[ESS]","timestamp":1439689654537,"level":-83,"frequency":2412},"2c:36:f8:0f:d3:2c":{"SSID":"utroam-1x","capabilities":"[WPA2-EAP-CCMP][ESS]","timestamp":1439689654586,"level":-82,"frequency":5200},"2c:36:f8:60:53:d5":{"SSID":"eng.ut-guest","capabilities":"[ESS]","timestamp":1439663745557,"level":-76,"frequency":2412},"dc:a5:f4:cc:13:f4":{"SSID":"eng.ut-1x","capabilities":"[WPA2-EAP-CCMP][ESS]","timestamp":1439689654529,"level":-82,"frequency":2412},"2c:36:f8:60:53:d2":{"SSID":"utroam","capabilities":"[WPA-PSK-CCMP][WPA2-PSK-CCMP][ESS]","timestamp":1439663745620,"level":-76,"frequency":2412},"dc:a5:f4:cc:13:f3":{"SSID":"utroam-1x","capabilities":"[WPA2-EAP-CCMP][ESS]","timestamp":1439689654531,"level":-82,"frequency":2412},"2c:36:f8:0f:d3:2a":{"SSID":"eng.ut-1x","capabilities":"[WPA2-EAP-CCMP][ESS]","timestamp":1439663746272,"level":-79,"frequency":5200},"dc:a5:f4:cc:13:f2":{"SSID":"utroam","capabilities":"[WPA-PSK-CCMP][WPA2-PSK-CCMP][ESS]","timestamp":1439689654533,"level":-82,"frequency":2412},"2c:36:f8:60:53:d0":{"SSID":"eng.ut","capabilities":"[WPA2-PSK-CCMP][ESS]","timestamp":1439663745589,"level":-78,"frequency":2412},"dc:a5:f4:cc:13:f1":{"SSID":"wnet.eng.ut","capabilities":"[WPA2-PSK-TKIP][ESS]","timestamp":1439689654535,"level":-82,"frequency":2412},"dc:a5:f4:cc:13:f0":{"SSID":"eng.ut","capabilities":"[WPA2-PSK-CCMP][ESS]","timestamp":1439689654526,"level":-80,"frequency":2412},"20:c9:d0:ab:4b:69":{"SSID":"","capabilities":"[WPA2-PSK-CCMP][ESS]","timestamp":1439663746897,"level":-90,"frequency":5500},"2c:36:f8:0f:d3:2f":{"SSID":"eng.ut","capabilities":"[WPA2-PSK-CCMP][ESS]","timestamp":1439663746319,"level":-77,"frequency":5200},"dc:a5:f4:cc:04:8a":{"SSID":"eng.ut-guest","capabilities":"[ESS]","timestamp":1439663746866,"level":-93,"frequency":5320},"c0:8a:de:5b:39:fc":{"SSID":"Wi2premium","capabilities":"[ESS]","timestamp":1439663746929,"level":-87,"frequency":5500},"a4:56:30:e9:3f:1a":{"SSID":"eng.ut-guest","capabilities":"[ESS]","timestamp":1439663746754,"level":-94,"frequency":5260},"a4:56:30:e9:3f:1b":{"SSID":"eng.ut-1x","capabilities":"[WPA2-EAP-CCMP][ESS]","timestamp":1439663746770,"level":-93,"frequency":5260},"10:bd:18:6d:e4:2c":{"SSID":"ist_members","capabilities":"[WPA2-PSK-CCMP][ESS]","timestamp":1439663746303,"level":-91,"frequency":5200},"2c:36:f8:60:49:1f":{"SSID":"eng.ut","capabilities":"[WPA2-PSK-CCMP][ESS]","timestamp":1439663746334,"level":-75,"frequency":5200},"2c:36:f8:60:49:1e":{"SSID":"wnet.eng.ut","capabilities":"[WPA2-PSK-TKIP][ESS]","timestamp":1439663746207,"level":-75,"frequency":5200},"dc:a5:f4:cc:04:8f":{"SSID":"eng.ut","capabilities":"[WPA2-PSK-CCMP][ESS]","timestamp":1439663746882,"level":-95,"frequency":5320},"2c:36:f8:0f:d6:e2":{"SSID":"utroam","capabilities":"[WPA-PSK-CCMP][WPA2-PSK-CCMP][ESS]","timestamp":1439689654558,"level":-63,"frequency":2462},"00:1d:73:90:d5:83":{"SSID":"MoodyNW","capabilities":"[WPA2-PSK-TKIP][ESS]","timestamp":1439663745635,"level":-80,"frequency":2422},"2c:36:f8:0f:d6:e0":{"SSID":"eng.ut","capabilities":"[WPA2-PSK-CCMP][ESS]","timestamp":1439689654551,"level":-65,"frequency":2462},"2c:36:f8:0f:d6:e5":{"SSID":"eng.ut-1x","capabilities":"[WPA2-EAP-CCMP][ESS]","timestamp":1439689654554,"level":-63,"frequency":2462},"06:3a:9d:b8:fc:f1":{"SSID":"WARPSTAR-991C6E-AW","capabilities":"[WEP][ESS]","timestamp":1439663746081,"level":-83,"frequency":5180},"34:bd:c8:55:fa:0d":{"SSID":"utroam","capabilities":"[WPA-PSK-CCMP][WPA2-PSK-CCMP][ESS]","timestamp":1439663746288,"level":-87,"frequency":5200},"2c:36:f8:0f:d6:e6":{"SSID":"sanshiro","capabilities":"[WPA2-PSK-CCMP][ESS]","timestamp":1439689654561,"level":-64,"frequency":2462},"2c:36:f8:0f:d6:e3":{"SSID":"utroam-1x","capabilities":"[WPA2-EAP-CCMP][ESS]","timestamp":1439663745968,"level":-75,"frequency":2462},"2c:36:f8:0f:d6:e4":{"SSID":"bld2-guest","capabilities":"[WEP][ESS]","timestamp":1439689654547,"level":-64,"frequency":2462},"00:16:01:05:f8:ce":{"SSID":"ZENKIJIKKEN","capabilities":"[WEP][ESS]","timestamp":1439663746457,"level":-92,"frequency":5220},"00:16:01:05:0c:f3":{"SSID":"SYSTEM6DESKWORKROOM","capabilities":"[WPA2-PSK-CCMP][ESS]","timestamp":1439663746801,"level":-91,"frequency":5280},"00:24:a5:e9:a8:0f":{"SSID":"yoshilab525-a","capabilities":"[WPA2-PSK-CCMP][WPS][ESS]","timestamp":1439663746818,"level":-93,"frequency":5280},"c0:8a:de:9b:39:fc":{"SSID":"Wi2premium_club","capabilities":"[WPA-PSK-CCMP+TKIP][WPA2-PSK-CCMP+TKIP][ESS]","timestamp":1439663746946,"level":-87,"frequency":5500},"2c:36:f8:0f:d6:e9":{"SSID":"sanshiro","capabilities":"[WPA2-PSK-CCMP][ESS]","timestamp":1439689654600,"level":-66,"frequency":5240},"2c:36:f8:0f:d6:e8":{"SSID":"eng.ut-guest","capabilities":"[ESS]","timestamp":1439689654556,"level":-65,"frequency":2462},"2c:36:f8:0f:d6:e7":{"SSID":"ist_members","capabilities":"[WPA2-PSK-CCMP][ESS]","timestamp":1439689654563,"level":-64,"frequency":2462},"3c:ce:73:49:7a:0d":{"SSID":"utroam-1x","capabilities":"[WPA2-EAP-CCMP][ESS]","timestamp":1439663746535,"level":-88,"frequency":5220},"3c:ce:73:49:7a:0b":{"SSID":"bld2-guest","capabilities":"[WEP][ESS]","timestamp":1439663746489,"level":-89,"frequency":5220},"2c:36:f8:0f:64:34":{"SSID":"bld2-guest","capabilities":"[WEP][ESS]","timestamp":1439689654549,"level":-87,"frequency":2462},"04:1e:64:fd:84:82":{"SSID":"Apple Network 015","capabilities":"[WPA-PSK-TKIP][WPA2-PSK-CCMP+TKIP][ESS]","timestamp":1439663746993,"level":-91,"frequency":5540},"c4:10:8a:5e:bc:9c":{"SSID":"Wi2premium","capabilities":"[ESS]","timestamp":1439663746978,"level":-91,"frequency":5540},"00:24:a5:89:4e:3a":{"SSID":"2D13B86363DB5B794602523063818BF4","capabilities":"[WPA-PSK-CCMP][ESS]","timestamp":1439663746256,"level":-80,"frequency":5200},"2c:36:f8:0f:d6:eb":{"SSID":"bld2-guest","capabilities":"[WEP][ESS]","timestamp":1439689654595,"level":-67,"frequency":5240},"2c:36:f8:0f:d6:ed":{"SSID":"utroam","capabilities":"[WPA-PSK-CCMP][WPA2-PSK-CCMP][ESS]","timestamp":1439689654598,"level":-66,"frequency":5240},"2c:36:f8:0f:d6:ef":{"SSID":"eng.ut","capabilities":"[WPA2-PSK-CCMP][ESS]","timestamp":1439689654591,"level":-66,"frequency":5240},"c0:8a:de:db:39:fc":{"SSID":"au_Wi-Fi2","capabilities":"[WPA2-EAP-CCMP][ESS]","timestamp":1439663746961,"level":-87,"frequency":5500},"a4:56:30:e8:d9:4c":{"SSID":"utroam-1x","capabilities":"[WPA2-EAP-CCMP][ESS]","timestamp":1439663746723,"level":-79,"frequency":5240},"2c:36:f8:60:23:5b":{"SSID":"bld2-guest","capabilities":"[WEP][ESS]","timestamp":1439689654574,"level":-81,"frequency":5200},"2c:36:f8:0f:64:3f":{"SSID":"eng.ut","capabilities":"[WPA2-PSK-CCMP][ESS]","timestamp":1439689654567,"level":-90,"frequency":5180},"2c:36:f8:60:23:5d":{"SSID":"utroam","capabilities":"[WPA-PSK-CCMP][WPA2-PSK-CCMP][ESS]","timestamp":1439689654577,"level":-80,"frequency":5200},"2c:36:f8:60:23:5f":{"SSID":"eng.ut","capabilities":"[WPA2-PSK-CCMP][ESS]","timestamp":1439689654570,"level":-80,"frequency":5200},"24:b6:57:74:d8:70":{"SSID":"rucolaAN","capabilities":"[WPA2-PSK-CCMP][ESS]","timestamp":1439663747010,"level":-87,"frequency":5560},"2c:36:f8:0f:ce:6f":{"SSID":"eng.ut","capabilities":"[WPA2-PSK-CCMP][ESS]","timestamp":1439663746096,"level":-89,"frequency":5180},"2c:36:f8:0e:6b:29":{"SSID":"sanshiro","capabilities":"[WPA2-PSK-CCMP][ESS]","timestamp":1439689654589,"level":-82,"frequency":5240},"00:16:01:05:fc:7c":{"SSID":"ZENKIJIKKEN","capabilities":"[WEP][ESS]","timestamp":1439663746443,"level":-87,"frequency":5220},"2c:36:f8:0f:f5:12":{"SSID":"utroam","capabilities":"[WPA-PSK-CCMP][WPA2-PSK-CCMP][ESS]","timestamp":1439663745834,"level":-77,"frequency":2462},"dc:a5:f4:cc:11:cb":{"SSID":"eng.ut-1x","capabilities":"[WPA2-EAP-CCMP][ESS]","timestamp":1439663746503,"level":-93,"frequency":5220},"2c:36:f8:0f:f5:18":{"SSID":"eng.ut-guest","capabilities":"[ESS]","timestamp":1439663745849,"level":-76,"frequency":2462},"b0:c7:45:32:02:60":{"SSID":"HRD0-G","capabilities":"[WPA2-PSK-CCMP][WPS][ESS]","timestamp":1439663745667,"level":-85,"frequency":2427},"2c:36:f8:0f:ce:67":{"SSID":"eng.ut-guest","capabilities":"[ESS]","timestamp":1439663746112,"level":-91,"frequency":5180},"00:24:a5:89:4e:38":{"SSID":"0024A5894E38_A","capabilities":"[WPA-PSK-CCMP+TKIP][WPA2-PSK-CCMP+TKIP][WPS][ESS]","timestamp":1439663746225,"level":-80,"frequency":5200},"10:6f:3f:37:6b:dc":{"SSID":"tkr Students","capabilities":"[WPA-PSK-CCMP+TKIP][WPA2-PSK-CCMP+TKIP][WPS][ESS]","timestamp":1439663745683,"level":-67,"frequency":2437},"34:bd:c8:55:fc:7d":{"SSID":"utroam","capabilities":"[WPA-PSK-CCMP][WPA2-PSK-CCMP][ESS]","timestamp":1439663746519,"level":-92,"frequency":5220},"34:bd:c8:55:fc:7b":{"SSID":"eng.ut-1x","capabilities":"[WPA2-EAP-CCMP][ESS]","timestamp":1439663746473,"level":-93,"frequency":5220},"00:0d:0b:d9:eb:eb":{"SSID":"ALABWireless133_A","capabilities":"[WPA-PSK-CCMP][ESS]","timestamp":1439663746176,"level":-88,"frequency":5180},"00:00:00:00:00:00":{"SSID":"","capabilities":"[ESS]","timestamp":1439663746785,"level":-92,"frequency":5280},"c0:8a:de:1b:39:fc":{"SSID":"au_Wi-Fi","capabilities":"[WPA2-PSK-CCMP][ESS]","timestamp":1439663746914,"level":-87,"frequency":5500},"88:1f:a1:35:4f:1a":{"SSID":"mpc_737","capabilities":"[WPA-PSK-TKIP][WPA2-PSK-CCMP+TKIP][ESS]","timestamp":1439663745573,"level":-72,"frequency":2412},"00:16:01:ef:97:b5":{"SSID":"wireless.me4stat_g","capabilities":"[WEP][ESS]","timestamp":1439663745819,"level":-80,"frequency":2447},"2c:36:f8:60:49:10":{"SSID":"eng.ut","capabilities":"[WPA2-PSK-CCMP][ESS]","timestamp":1439663745803,"level":-79,"frequency":2437},"2c:36:f8:60:53:da":{"SSID":"eng.ut-guest","capabilities":"[ESS]","timestamp":1439663746707,"level":-82,"frequency":5240},"2c:36:f8:60:53:dd":{"SSID":"utroam","capabilities":"[WPA-PSK-CCMP][WPA2-PSK-CCMP][ESS]","timestamp":1439663746675,"level":-82,"frequency":5240},"2c:36:f8:60:53:de":{"SSID":"wnet.eng.ut","capabilities":"[WPA2-PSK-TKIP][ESS]","timestamp":1439663746691,"level":-79,"frequency":5240},"2c:36:f8:60:53:df":{"SSID":"eng.ut","capabilities":"[WPA2-PSK-CCMP][ESS]","timestamp":1439663746551,"level":-85,"frequency":5240},"2c:36:f8:60:23:57":{"SSID":"eng.ut-guest","capabilities":"[ESS]","timestamp":1439689654572,"level":-80,"frequency":5200},"2c:36:f8:60:23:58":{"SSID":"ist_members","capabilities":"[WPA2-PSK-CCMP][ESS]","timestamp":1439689654581,"level":-80,"frequency":5200},"2c:36:f8:60:23:59":{"SSID":"sanshiro","capabilities":"[WPA2-PSK-CCMP][ESS]","timestamp":1439689654579,"level":-80,"frequency":5200},"2c:36:f8:0f:fe:b9":{"SSID":"sanshiro","capabilities":"[WPA2-PSK-CCMP][ESS]","timestamp":1439663746412,"level":-81,"frequency":5220},"2c:36:f8:0f:fe:b3":{"SSID":"utroam-1x","capabilities":"[WPA2-EAP-CCMP][ESS]","timestamp":1439663745759,"level":-78,"frequency":2437},"2c:36:f8:0f:d3:20":{"SSID":"eng.ut","capabilities":"[WPA2-PSK-CCMP][ESS]","timestamp":1439689654542,"level":-84,"frequency":2437},"2c:36:f8:0f:fe:b7":{"SSID":"eng.ut-guest","capabilities":"[ESS]","timestamp":1439663746365,"level":-81,"frequency":5220},"2c:36:f8:0f:fe:b8":{"SSID":"ist_members","capabilities":"[WPA2-PSK-CCMP][ESS]","timestamp":1439663746428,"level":-81,"frequency":5220},"1c:b1:7f:e0:d6:7e":{"SSID":"sl-intra-a-g","capabilities":"[WPA2-PSK-CCMP][WPS][ESS]","timestamp":1439663745651,"level":-86,"frequency":2422},"a4:56:30:e8:de:9f":{"SSID":"eng.ut","capabilities":"[WPA2-PSK-CCMP][ESS]","timestamp":1439663746851,"level":-95,"frequency":5300},"88:1f:a1:35:4f:1b":{"SSID":"mpc_737","capabilities":"[WPA-PSK-TKIP][WPA2-PSK-CCMP+TKIP][ESS]","timestamp":1439663746129,"level":-91,"frequency":5180},"2c:36:f8:60:65:df":{"SSID":"eng.ut","capabilities":"[WPA2-PSK-CCMP][ESS]","timestamp":1439663746659,"level":-83,"frequency":5240},"a4:56:30:e8:de:9c":{"SSID":"utroam-1x","capabilities":"[WPA2-EAP-CCMP][ESS]","timestamp":1439663746835,"level":-94,"frequency":5300},"2c:36:f8:60:65:db":{"SSID":"eng.ut-1x","capabilities":"[WPA2-EAP-CCMP][ESS]","timestamp":1439663746738,"level":-83,"frequency":5240}},"magnetic":{"x":-45.046997,"y":30.308533,"z":8.764648},"gravity":{"x":8.965052,"y":3.9594133,"z":-0.34826276}},"location":{"floor":"2F","accuracy":0.5,"latitude":35.71449033137577,"longitude":139.7616297751665}},{"fingerprint":{"pressure":1022.49805,"wifi":{"2c:36:f8:60:23:5b":{"SSID":"bld2-guest","capabilities":"[WEP][ESS]","timestamp":1439689654574,"level":-81,"frequency":5200},"2c:36:f8:0f:64:3f":{"SSID":"eng.ut","capabilities":"[WPA2-PSK-CCMP][ESS]","timestamp":1439701297074,"level":-79,"frequency":5180},"2c:36:f8:60:23:5d":{"SSID":"utroam","capabilities":"[WPA-PSK-CCMP][WPA2-PSK-CCMP][ESS]","timestamp":1439689654577,"level":-80,"frequency":5200},"2c:36:f8:0f:64:3a":{"SSID":"eng.ut-1x","capabilities":"[WPA2-EAP-CCMP][ESS]","timestamp":1439701297082,"level":-78,"frequency":5180},"2c:36:f8:0f:64:3b":{"SSID":"bld2-guest","capabilities":"[WEP][ESS]","timestamp":1439701297086,"level":-78,"frequency":5180},"2c:36:f8:60:23:5f":{"SSID":"eng.ut","capabilities":"[WPA2-PSK-CCMP][ESS]","timestamp":1439689654570,"level":-80,"frequency":5200},"2c:36:f8:0f:64:3d":{"SSID":"utroam","capabilities":"[WPA-PSK-CCMP][WPA2-PSK-CCMP][ESS]","timestamp":1439701297089,"level":-79,"frequency":5180},"2c:36:f8:0e:6b:29":{"SSID":"sanshiro","capabilities":"[WPA2-PSK-CCMP][ESS]","timestamp":1439701297120,"level":-77,"frequency":5240},"2c:36:f8:0e:6b:27":{"SSID":"eng.ut-guest","capabilities":"[ESS]","timestamp":1439701297136,"level":-78,"frequency":5240},"2c:36:f8:0e:6b:28":{"SSID":"ist_members","capabilities":"[WPA2-PSK-CCMP][ESS]","timestamp":1439701297143,"level":-78,"frequency":5240},"2c:36:f8:0f:d3:23":{"SSID":"utroam-1x","capabilities":"[WPA2-EAP-CCMP][ESS]","timestamp":1439689654540,"level":-85,"frequency":2437},"dc:a5:f4:cc:13:fa":{"SSID":"eng.ut-guest","capabilities":"[ESS]","timestamp":1439689654565,"level":-84,"frequency":5180},"2c:36:f8:0f:d3:28":{"SSID":"ist_members","capabilities":"[WPA2-PSK-CCMP][ESS]","timestamp":1439701297105,"level":-88,"frequency":5200},"2c:36:f8:0e:6b:2d":{"SSID":"utroam","capabilities":"[WPA-PSK-CCMP][WPA2-PSK-CCMP][ESS]","timestamp":1439701297116,"level":-77,"frequency":5240},"dc:a5:f4:cc:13:f5":{"SSID":"eng.ut-guest","capabilities":"[ESS]","timestamp":1439689654537,"level":-83,"frequency":2412},"2c:36:f8:0f:d3:2c":{"SSID":"utroam-1x","capabilities":"[WPA2-EAP-CCMP][ESS]","timestamp":1439689654586,"level":-82,"frequency":5200},"2c:36:f8:0e:6b:2f":{"SSID":"eng.ut","capabilities":"[WPA2-PSK-CCMP][ESS]","timestamp":1439701297113,"level":-76,"frequency":5240},"dc:a5:f4:cc:13:f4":{"SSID":"eng.ut-1x","capabilities":"[WPA2-EAP-CCMP][ESS]","timestamp":1439689654529,"level":-82,"frequency":2412},"dc:a5:f4:cc:13:f3":{"SSID":"utroam-1x","capabilities":"[WPA2-EAP-CCMP][ESS]","timestamp":1439689654531,"level":-82,"frequency":2412},"dc:a5:f4:cc:13:f2":{"SSID":"utroam","capabilities":"[WPA-PSK-CCMP][WPA2-PSK-CCMP][ESS]","timestamp":1439689654533,"level":-82,"frequency":2412},"dc:a5:f4:cc:13:f1":{"SSID":"wnet.eng.ut","capabilities":"[WPA2-PSK-TKIP][ESS]","timestamp":1439689654535,"level":-82,"frequency":2412},"2c:36:f8:0e:6b:2b":{"SSID":"bld2-guest","capabilities":"[WEP][ESS]","timestamp":1439701297140,"level":-79,"frequency":5240},"dc:a5:f4:cc:13:f0":{"SSID":"eng.ut","capabilities":"[WPA2-PSK-CCMP][ESS]","timestamp":1439689654526,"level":-80,"frequency":2412},"2c:36:f8:60:23:5a":{"SSID":"eng.ut-1x","capabilities":"[WPA2-EAP-CCMP][ESS]","timestamp":1439701297101,"level":-85,"frequency":5200},"00:24:a5:7c:5e:a0":{"SSID":"FELB11A1","capabilities":"[WPA2-PSK-CCMP][WPS][ESS]","timestamp":1439701297047,"level":-89,"frequency":2437},"2c:36:f8:0f:d6:e2":{"SSID":"utroam","capabilities":"[WPA-PSK-CCMP][WPA2-PSK-CCMP][ESS]","timestamp":1439701297051,"level":-77,"frequency":2462},"00:00:00:00:00:00":{"SSID":"","capabilities":"[ESS]","timestamp":1439663746785,"level":-92,"frequency":5280},"2c:36:f8:60:23:50":{"SSID":"eng.ut","capabilities":"[WPA2-PSK-CCMP][ESS]","timestamp":1439701297032,"level":-81,"frequency":2412},"2c:36:f8:0f:d6:e0":{"SSID":"eng.ut","capabilities":"[WPA2-PSK-CCMP][ESS]","timestamp":1439701297070,"level":-69,"frequency":2462},"2c:36:f8:0f:d6:e5":{"SSID":"eng.ut-1x","capabilities":"[WPA2-EAP-CCMP][ESS]","timestamp":1439701297055,"level":-72,"frequency":2462},"2c:36:f8:0f:d6:e6":{"SSID":"sanshiro","capabilities":"[WPA2-PSK-CCMP][ESS]","timestamp":1439701297066,"level":-69,"frequency":2462},"2c:36:f8:0f:d6:e4":{"SSID":"bld2-guest","capabilities":"[WEP][ESS]","timestamp":1439701297063,"level":-75,"frequency":2462},"00:1d:73:21:13:c0":{"SSID":"ZENKIJIKKEN","capabilities":"[WEP][ESS]","timestamp":1439701297043,"level":-86,"frequency":2432},"2c:36:f8:60:23:57":{"SSID":"eng.ut-guest","capabilities":"[ESS]","timestamp":1439689654572,"level":-80,"frequency":5200},"2c:36:f8:0f:d6:e9":{"SSID":"sanshiro","capabilities":"[WPA2-PSK-CCMP][ESS]","timestamp":1439701297124,"level":-79,"frequency":5240},"2c:36:f8:60:23:58":{"SSID":"eng.ut-guest","capabilities":"[ESS]","timestamp":1439701297036,"level":-81,"frequency":2412},"2c:36:f8:0f:d6:e8":{"SSID":"eng.ut-guest","capabilities":"[ESS]","timestamp":1439701297059,"level":-73,"frequency":2462},"2c:36:f8:60:23:59":{"SSID":"sanshiro","capabilities":"[WPA2-PSK-CCMP][ESS]","timestamp":1439689654579,"level":-80,"frequency":5200},"2c:36:f8:0f:d6:e7":{"SSID":"ist_members","capabilities":"[WPA2-PSK-CCMP][ESS]","timestamp":1439701297147,"level":-75,"frequency":2462},"2c:36:f8:60:23:54":{"SSID":"bld2-guest","capabilities":"[WEP][ESS]","timestamp":1439701297039,"level":-81,"frequency":2412},"2c:36:f8:60:23:55":{"SSID":"eng.ut-1x","capabilities":"[WPA2-EAP-CCMP][ESS]","timestamp":1439701297029,"level":-81,"frequency":2412},"2c:36:f8:0f:64:37":{"SSID":"eng.ut-guest","capabilities":"[ESS]","timestamp":1439701297078,"level":-78,"frequency":5180},"2c:36:f8:0f:64:38":{"SSID":"ist_members","capabilities":"[WPA2-PSK-CCMP][ESS]","timestamp":1439701297097,"level":-78,"frequency":5180},"3c:ce:73:49:7a:0d":{"SSID":"utroam-1x","capabilities":"[WPA2-EAP-CCMP][ESS]","timestamp":1439701297109,"level":-91,"frequency":5220},"2c:36:f8:0f:64:34":{"SSID":"bld2-guest","capabilities":"[WEP][ESS]","timestamp":1439689654549,"level":-87,"frequency":2462},"2c:36:f8:0f:d3:20":{"SSID":"eng.ut","capabilities":"[WPA2-PSK-CCMP][ESS]","timestamp":1439689654542,"level":-84,"frequency":2437},"2c:36:f8:0f:64:39":{"SSID":"sanshiro","capabilities":"[WPA2-PSK-CCMP][ESS]","timestamp":1439701297093,"level":-79,"frequency":5180},"2c:36:f8:0f:d6:eb":{"SSID":"bld2-guest","capabilities":"[WEP][ESS]","timestamp":1439701297132,"level":-80,"frequency":5240},"2c:36:f8:0f:d6:ed":{"SSID":"utroam","capabilities":"[WPA-PSK-CCMP][WPA2-PSK-CCMP][ESS]","timestamp":1439689654598,"level":-66,"frequency":5240},"2c:36:f8:0f:d6:ef":{"SSID":"eng.ut","capabilities":"[WPA2-PSK-CCMP][ESS]","timestamp":1439689654591,"level":-66,"frequency":5240}},"magnetic":{"x":-32.788086,"y":45.951843,"z":-38.81378},"gravity":{"x":9.169939,"y":-3.4693894,"z":-0.21432188}},"location":{"floor":"2F","accuracy":0.5,"latitude":35.71445167573862,"longitude":139.76165659725666}},{"fingerprint":{"pressure":1022.458,"wifi":{"2c:36:f8:60:23:5c":{"SSID":"utroam-1x","capabilities":"[WPA2-EAP-CCMP][ESS]","timestamp":1439711307196,"level":-86,"frequency":5200},"2c:36:f8:0f:64:3f":{"SSID":"eng.ut","capabilities":"[WPA2-PSK-CCMP][ESS]","timestamp":1439711307161,"level":-69,"frequency":5180},"2c:36:f8:0f:64:3a":{"SSID":"eng.ut-1x","capabilities":"[WPA2-EAP-CCMP][ESS]","timestamp":1439701297082,"level":-78,"frequency":5180},"2c:36:f8:0f:64:3b":{"SSID":"bld2-guest","capabilities":"[WEP][ESS]","timestamp":1439711307172,"level":-70,"frequency":5180},"2c:36:f8:0f:64:3c":{"SSID":"utroam-1x","capabilities":"[WPA2-EAP-CCMP][ESS]","timestamp":1439711307184,"level":-70,"frequency":5180},"2c:36:f8:0f:64:3d":{"SSID":"utroam","capabilities":"[WPA-PSK-CCMP][WPA2-PSK-CCMP][ESS]","timestamp":1439711307176,"level":-69,"frequency":5180},"2c:36:f8:0f:d3:29":{"SSID":"sanshiro","capabilities":"[WPA2-PSK-CCMP][ESS]","timestamp":1439711307192,"level":-87,"frequency":5200},"3c:ce:73:49:7a:02":{"SSID":"utroam-1x","capabilities":"[WPA2-EAP-CCMP][ESS]","timestamp":1439711307073,"level":-89,"frequency":2412},"2c:36:f8:0e:6b:29":{"SSID":"sanshiro","capabilities":"[WPA2-PSK-CCMP][ESS]","timestamp":1439711307219,"level":-74,"frequency":5240},"2c:36:f8:0e:6b:27":{"SSID":"eng.ut-guest","capabilities":"[ESS]","timestamp":1439711307208,"level":-75,"frequency":5240},"2c:36:f8:0e:6b:28":{"SSID":"ist_members","capabilities":"[WPA2-PSK-CCMP][ESS]","timestamp":1439711307223,"level":-75,"frequency":5240},"2c:36:f8:0e:6b:25":{"SSID":"eng.ut-1x","capabilities":"[WPA2-EAP-CCMP][ESS]","timestamp":1439711307069,"level":-70,"frequency":2412},"2c:36:f8:0f:d3:23":{"SSID":"utroam-1x","capabilities":"[WPA2-EAP-CCMP][ESS]","timestamp":1439711307106,"level":-80,"frequency":2437},"2c:36:f8:0f:d3:24":{"SSID":"bld2-guest","capabilities":"[WEP][ESS]","timestamp":1439711307129,"level":-80,"frequency":2437},"2c:36:f8:0f:d3:25":{"SSID":"eng.ut-1x","capabilities":"[WPA2-EAP-CCMP][ESS]","timestamp":1439711307084,"level":-79,"frequency":2437},"2c:36:f8:0f:d3:27":{"SSID":"ist_members","capabilities":"[WPA2-PSK-CCMP][ESS]","timestamp":1439711307099,"level":-80,"frequency":2437},"2c:36:f8:0f:d3:28":{"SSID":"ist_members","capabilities":"[WPA2-PSK-CCMP][ESS]","timestamp":1439701297105,"level":-88,"frequency":5200},"2c:36:f8:0e:6b:2d":{"SSID":"utroam","capabilities":"[WPA-PSK-CCMP][WPA2-PSK-CCMP][ESS]","timestamp":1439711307215,"level":-74,"frequency":5240},"2c:36:f8:0e:6b:2f":{"SSID":"eng.ut","capabilities":"[WPA2-PSK-CCMP][ESS]","timestamp":1439711307204,"level":-75,"frequency":5240},"2c:36:f8:0e:6b:2b":{"SSID":"bld2-guest","capabilities":"[WEP][ESS]","timestamp":1439711307212,"level":-74,"frequency":5240},"2c:36:f8:60:23:5a":{"SSID":"eng.ut-1x","capabilities":"[WPA2-EAP-CCMP][ESS]","timestamp":1439701297101,"level":-85,"frequency":5200},"00:24:a5:7c:5e:a0":{"SSID":"FELB11A1","capabilities":"[WPA2-PSK-CCMP][WPS][ESS]","timestamp":1439701297047,"level":-89,"frequency":2437},"2c:36:f8:0f:d6:e2":{"SSID":"utroam","capabilities":"[WPA-PSK-CCMP][WPA2-PSK-CCMP][ESS]","timestamp":1439701297051,"level":-77,"frequency":2462},"00:00:00:00:00:00":{"SSID":"","capabilities":"[ESS]","timestamp":1439663746785,"level":-92,"frequency":5280},"2c:36:f8:60:23:50":{"SSID":"eng.ut","capabilities":"[WPA2-PSK-CCMP][ESS]","timestamp":1439711307077,"level":-83,"frequency":2412},"2c:36:f8:0f:d6:e0":{"SSID":"eng.ut","capabilities":"[WPA2-PSK-CCMP][ESS]","timestamp":1439711307157,"level":-79,"frequency":2462},"2c:36:f8:0f:d6:e5":{"SSID":"eng.ut-1x","capabilities":"[WPA2-EAP-CCMP][ESS]","timestamp":1439701297055,"level":-72,"frequency":2462},"2c:36:f8:0f:d6:e6":{"SSID":"sanshiro","capabilities":"[WPA2-PSK-CCMP][ESS]","timestamp":1439701297066,"level":-69,"frequency":2462},"2c:36:f8:0f:d6:e4":{"SSID":"bld2-guest","capabilities":"[WEP][ESS]","timestamp":1439701297063,"level":-75,"frequency":2462},"00:1d:73:21:13:c0":{"SSID":"ZENKIJIKKEN","capabilities":"[WEP][ESS]","timestamp":1439701297043,"level":-86,"frequency":2432},"00:16:01:05:f8:ce":{"SSID":"ZENKIJIKKEN","capabilities":"[WEP][ESS]","timestamp":1439711307200,"level":-87,"frequency":5220},"2c:36:f8:0f:d6:e9":{"SSID":"sanshiro","capabilities":"[WPA2-PSK-CCMP][ESS]","timestamp":1439701297124,"level":-79,"frequency":5240},"2c:36:f8:60:23:58":{"SSID":"eng.ut-guest","capabilities":"[ESS]","timestamp":1439711307080,"level":-83,"frequency":2412},"2c:36:f8:0f:d6:e8":{"SSID":"eng.ut-guest","capabilities":"[ESS]","timestamp":1439701297059,"level":-73,"frequency":2462},"2c:36:f8:0f:d6:e7":{"SSID":"ist_members","capabilities":"[WPA2-PSK-CCMP][ESS]","timestamp":1439711307088,"level":-79,"frequency":2462},"2c:36:f8:60:23:54":{"SSID":"bld2-guest","capabilities":"[WEP][ESS]","timestamp":1439701297039,"level":-81,"frequency":2412},"00:0a:79:6d:c6:cb":{"SSID":"quadrot","capabilities":"[WEP][ESS]","timestamp":1439711307095,"level":-80,"frequency":2437},"2c:36:f8:60:23:55":{"SSID":"eng.ut-1x","capabilities":"[WPA2-EAP-CCMP][ESS]","timestamp":1439701297029,"level":-81,"frequency":2412},"2c:36:f8:0f:d2:23":{"SSID":"utroam-1x","capabilities":"[WPA2-EAP-CCMP][ESS]","timestamp":1439711307091,"level":-89,"frequency":2437},"2c:36:f8:0f:64:37":{"SSID":"ist_members","capabilities":"[WPA2-PSK-CCMP][ESS]","timestamp":1439711307153,"level":-65,"frequency":2462},"2c:36:f8:0f:64:38":{"SSID":"eng.ut-guest","capabilities":"[ESS]","timestamp":1439711307141,"level":-65,"frequency":2462},"3c:ce:73:49:7a:0d":{"SSID":"utroam-1x","capabilities":"[WPA2-EAP-CCMP][ESS]","timestamp":1439701297109,"level":-91,"frequency":5220},"2c:36:f8:0f:64:36":{"SSID":"sanshiro","capabilities":"[WPA2-PSK-CCMP][ESS]","timestamp":1439711307149,"level":-65,"frequency":2462},"2c:36:f8:0f:64:34":{"SSID":"bld2-guest","capabilities":"[WEP][ESS]","timestamp":1439711307137,"level":-69,"frequency":2462},"2c:36:f8:0f:64:32":{"SSID":"utroam","capabilities":"[WPA-PSK-CCMP][WPA2-PSK-CCMP][ESS]","timestamp":1439711307145,"level":-65,"frequency":2462},"2c:36:f8:0f:d3:20":{"SSID":"eng.ut","capabilities":"[WPA2-PSK-CCMP][ESS]","timestamp":1439711307102,"level":-80,"frequency":2437},"2c:36:f8:0f:64:39":{"SSID":"sanshiro","capabilities":"[WPA2-PSK-CCMP][ESS]","timestamp":1439711307180,"level":-69,"frequency":5180},"2c:36:f8:0f:d6:eb":{"SSID":"bld2-guest","capabilities":"[WEP][ESS]","timestamp":1439701297132,"level":-80,"frequency":5240},"2c:36:f8:0f:d6:ef":{"SSID":"eng.ut","capabilities":"[WPA2-PSK-CCMP][ESS]","timestamp":1439711307227,"level":-80,"frequency":5240},"2c:36:f8:0f:64:30":{"SSID":"eng.ut","capabilities":"[WPA2-PSK-CCMP][ESS]","timestamp":1439711307134,"level":-65,"frequency":2462}},"magnetic":{"x":-12.496948,"y":-6.588745,"z":11.672974},"gravity":{"x":-9.779584,"y":0.6876192,"z":0.23936781}},"location":{"floor":"2F","accuracy":0.5,"latitude":35.71448570358922,"longitude":139.76168643683195}}]