[{"fingerprint":{"pressure":-1.0,"wifi":{"00:20:a6:5d:64:0d":{"SSID":"yw6IUmTS","capabilities":"[WEP][ESS]","timestamp":52980771839,"level":-61,"frequency":2437},"3c:ce:73:49:7a:02":{"SSID":"utroam-1x","capabilities":"[WPA2-EAP-CCMP][ESS]","timestamp":52980771691,"level":-66,"frequency":2412},"3c:ce:73:49:7a:01":{"SSID":"utroam","capabilities":"[WPA-PSK-CCMP][WPA2-PSK-CCMP][ESS]","timestamp":52980771713,"level":-66,"frequency":2412},"3c:ce:73:49:7a:04":{"SSID":"bld2-guest","capabilities":"[WEP][ESS]","timestamp":52980771702,"level":-66,"frequency":2412},"2c:36:f8:0f:fe:b0":{"SSID":"eng.ut","capabilities":"[WPA2-PSK-CCMP][ESS]","timestamp":52980771798,"level":-69,"frequency":2437},"3c:ce:73:49:7a:03":{"SSID":"ist_members","capabilities":"[WPA2-PSK-CCMP][ESS]","timestamp":52980771724,"level":-65,"frequency":2412},"00:24:14:ff:f4:b1":{"SSID":"UTnet-wireless","capabilities":"[WPA2-PSK-CCMP][ESS]","timestamp":52980772210,"level":-71,"frequency":2462},"00:24:14:ff:f4:b2":{"SSID":"0001softbank","capabilities":"[ESS]","timestamp":52980772185,"level":-57,"frequency":2462},"10:6f:3f:f2:41:6c":{"SSID":"106F3FF2416C","capabilities":"[WPA-PSK-CCMP+TKIP][WPA2-PSK-CCMP+TKIP][WPS][ESS]","timestamp":52980771818,"level":-77,"frequency":2422},"2c:36:f8:0e:6b:26":{"SSID":"sanshiro","capabilities":"[WPA2-PSK-CCMP][ESS]","timestamp":52980772155,"level":-77,"frequency":2437},"00:24:14:ff:f4:b0":{"SSID":"","capabilities":"[WEP][ESS]","timestamp":52980772138,"level":-73,"frequency":2462},"2c:36:f8:0e:6b:22":{"SSID":"utroam","capabilities":"[WPA-PSK-CCMP][WPA2-PSK-CCMP][ESS]","timestamp":52980771858,"level":-76,"frequency":2437},"2c:36:f8:0e:6b:20":{"SSID":"eng.ut","capabilities":"[WPA2-PSK-CCMP][ESS]","timestamp":52980771904,"level":-77,"frequency":2437},"2c:36:f8:60:50:92":{"SSID":"utroam","capabilities":"[WPA-PSK-CCMP][WPA2-PSK-CCMP][ESS]","timestamp":52980771895,"level":-71,"frequency":2437},"2c:36:f8:60:50:93":{"SSID":"utroam-1x","capabilities":"[WPA2-EAP-CCMP][ESS]","timestamp":52980771756,"level":-72,"frequency":2437},"2c:36:f8:60:50:90":{"SSID":"eng.ut","capabilities":"[WPA2-PSK-CCMP][ESS]","timestamp":52980771829,"level":-71,"frequency":2437},"2c:36:f8:60:50:91":{"SSID":"wnet.eng.ut","capabilities":"[WPA2-PSK-TKIP][ESS]","timestamp":52980771847,"level":-72,"frequency":2437},"2c:36:f8:60:50:94":{"SSID":"eng.ut-1x","capabilities":"[WPA2-EAP-CCMP][ESS]","timestamp":52980771885,"level":-72,"frequency":2437},"2c:36:f8:60:50:95":{"SSID":"eng.ut-guest","capabilities":"[ESS]","timestamp":52980771786,"level":-71,"frequency":2437},"00:20:a6:5d:87:01":{"SSID":"yw6IUmTS","capabilities":"[WEP][ESS]","timestamp":52980771678,"level":-66,"frequency":2412},"2c:36:f8:0f:fe:b3":{"SSID":"utroam-1x","capabilities":"[WPA2-EAP-CCMP][ESS]","timestamp":52980771735,"level":-70,"frequency":2437},"2c:36:f8:0f:fe:b4":{"SSID":"bld2-guest","capabilities":"[WEP][ESS]","timestamp":52980771868,"level":-69,"frequency":2437},"2c:36:f8:0f:fe:b7":{"SSID":"ist_members","capabilities":"[WPA2-PSK-CCMP][ESS]","timestamp":52980771915,"level":-70,"frequency":2437},"2c:36:f8:0f:fe:b8":{"SSID":"eng.ut-guest","capabilities":"[ESS]","timestamp":52980772172,"level":-71,"frequency":2437},"00:07:40:ed:62:04":{"SSID":"000740E604CF","capabilities":"[WEP][ESS]","timestamp":52980771809,"level":-77,"frequency":2422},"2c:36:f8:0f:fe:b5":{"SSID":"eng.ut-1x","capabilities":"[WPA2-EAP-CCMP][ESS]","timestamp":52980771766,"level":-74,"frequency":2437},"10:bd:18:6d:e3:51":{"SSID":"utroam","capabilities":"[WPA-PSK-CCMP][WPA2-PSK-CCMP][ESS]","timestamp":52980771877,"level":-72,"frequency":2437},"32:f3:1d:4a:4b:5f":{"SSID":"EMOBILE-GL09P-4B5F","capabilities":"[WPA-PSK-CCMP+TKIP][WPA2-PSK-CCMP+TKIP][WPS][ESS]","timestamp":52980772124,"level":-77,"frequency":2437},"10:bd:18:6d:e3:52":{"SSID":"utroam-1x","capabilities":"[WPA2-EAP-CCMP][ESS]","timestamp":52980771777,"level":-76,"frequency":2437},"10:bd:18:6d:e3:50":{"SSID":"eng.ut","capabilities":"[WPA2-PSK-CCMP][ESS]","timestamp":52980771665,"level":-73,"frequency":2437},"10:bd:18:6d:e3:53":{"SSID":"ist_members","capabilities":"[WPA2-PSK-CCMP][ESS]","timestamp":52980772109,"level":-72,"frequency":2437},"10:bd:18:6d:e3:54":{"SSID":"bld2-guest","capabilities":"[WEP][ESS]","timestamp":52980771746,"level":-72,"frequency":2437}},"magnetic":{"x":-34.997868,"y":-12.6658945,"z":-8.832795},"gravity":{"x":1.1851299,"y":4.3505635,"z":8.70846}},"location":{"floor":"4F","accuracy":0.5,"latitude":35.71432971980271,"longitude":139.76160932332277}},{"fingerprint":{"pressure":-1.0,"wifi":{"2c:36:f8:0f:da:90":{"SSID":"eng.ut","capabilities":"[WPA2-PSK-CCMP][ESS]","timestamp":52987753692,"level":-57,"frequency":2462},"00:1d:73:21:13:c0":{"SSID":"ZENKIJIKKEN","capabilities":"[WEP][ESS]","timestamp":52987753575,"level":-63,"frequency":2417},"2c:36:f8:0f:da:94":{"SSID":"bld2-guest","capabilities":"[WEP][ESS]","timestamp":52987753697,"level":-56,"frequency":2462},"2c:36:f8:0f:da:95":{"SSID":"eng.ut-1x","capabilities":"[WPA2-EAP-CCMP][ESS]","timestamp":52987753668,"level":-57,"frequency":2462},"00:20:a6:5d:64:0d":{"SSID":"yw6IUmTS","capabilities":"[WEP][ESS]","timestamp":52987753626,"level":-61,"frequency":2437},"2c:36:f8:0f:da:98":{"SSID":"eng.ut-guest","capabilities":"[ESS]","timestamp":52987753664,"level":-54,"frequency":2462},"3c:ce:73:49:7a:00":{"SSID":"eng.ut","capabilities":"[WPA2-PSK-CCMP][ESS]","timestamp":52987753553,"level":-62,"frequency":2412},"3c:ce:73:49:7a:02":{"SSID":"utroam-1x","capabilities":"[WPA2-EAP-CCMP][ESS]","timestamp":52987753580,"level":-60,"frequency":2412},"3c:ce:73:49:7a:01":{"SSID":"utroam","capabilities":"[WPA-PSK-CCMP][WPA2-PSK-CCMP][ESS]","timestamp":52987753564,"level":-62,"frequency":2412},"3c:ce:73:49:7a:04":{"SSID":"bld2-guest","capabilities":"[WEP][ESS]","timestamp":52987753558,"level":-61,"frequency":2412},"2c:36:f8:0f:fe:b0":{"SSID":"eng.ut","capabilities":"[WPA2-PSK-CCMP][ESS]","timestamp":52987753606,"level":-67,"frequency":2437},"3c:ce:73:49:7a:03":{"SSID":"ist_members","capabilities":"[WPA2-PSK-CCMP][ESS]","timestamp":52987753570,"level":-62,"frequency":2412},"00:24:14:ff:f4:b1":{"SSID":"UTnet-wireless","capabilities":"[WPA2-PSK-CCMP][ESS]","timestamp":52987753682,"level":-68,"frequency":2462},"00:24:14:ff:f4:b2":{"SSID":"0001softbank","capabilities":"[ESS]","timestamp":52987753660,"level":-62,"frequency":2462},"10:6f:3f:f2:41:6c":{"SSID":"106F3FF2416C","capabilities":"[WPA-PSK-CCMP+TKIP][WPA2-PSK-CCMP+TKIP][WPS][ESS]","timestamp":52980771818,"level":-77,"frequency":2422},"2c:36:f8:0e:6b:26":{"SSID":"sanshiro","capabilities":"[WPA2-PSK-CCMP][ESS]","timestamp":52980772155,"level":-77,"frequency":2437},"04:fe:7f:93:6e:13":{"SSID":"upa48","capabilities":"[WPA2-PSK-CCMP][ESS]","timestamp":52987753590,"level":-81,"frequency":2437},"00:24:14:ff:f4:b0":{"SSID":"","capabilities":"[WEP][ESS]","timestamp":52980772138,"level":-73,"frequency":2462},"00:24:14:ff:f4:b6":{"SSID":"docomo","capabilities":"[WEP][ESS]","timestamp":52987753678,"level":-69,"frequency":2462},"2c:36:f8:0e:6b:22":{"SSID":"utroam","capabilities":"[WPA-PSK-CCMP][WPA2-PSK-CCMP][ESS]","timestamp":52980771858,"level":-76,"frequency":2437},"00:24:14:ff:f4:b3":{"SSID":"SWS1day","capabilities":"[ESS]","timestamp":52987753688,"level":-68,"frequency":2462},"2c:36:f8:0e:6b:20":{"SSID":"eng.ut","capabilities":"[WPA2-PSK-CCMP][ESS]","timestamp":52980771904,"level":-77,"frequency":2437},"2c:36:f8:60:50:92":{"SSID":"utroam","capabilities":"[WPA-PSK-CCMP][WPA2-PSK-CCMP][ESS]","timestamp":52987753631,"level":-75,"frequency":2437},"2c:36:f8:60:50:93":{"SSID":"utroam-1x","capabilities":"[WPA2-EAP-CCMP][ESS]","timestamp":52980771756,"level":-72,"frequency":2437},"2c:36:f8:60:50:90":{"SSID":"eng.ut","capabilities":"[WPA2-PSK-CCMP][ESS]","timestamp":52987753702,"level":-75,"frequency":2437},"2c:36:f8:60:50:91":{"SSID":"wnet.eng.ut","capabilities":"[WPA2-PSK-TKIP][ESS]","timestamp":52987753535,"level":-77,"frequency":2437},"00:24:14:ff:f4:b7":{"SSID":"0000docomo","capabilities":"[WPA2-PSK-CCMP][ESS]","timestamp":52987753673,"level":-63,"frequency":2462},"2c:36:f8:60:50:94":{"SSID":"eng.ut-1x","capabilities":"[WPA2-EAP-CCMP][ESS]","timestamp":52980771885,"level":-72,"frequency":2437},"2c:36:f8:60:50:95":{"SSID":"eng.ut-guest","capabilities":"[ESS]","timestamp":52987753601,"level":-76,"frequency":2437},"00:20:a6:5d:87:01":{"SSID":"yw6IUmTS","capabilities":"[WEP][ESS]","timestamp":52987753547,"level":-65,"frequency":2412},"2c:36:f8:0f:fe:b3":{"SSID":"utroam-1x","capabilities":"[WPA2-EAP-CCMP][ESS]","timestamp":52987753585,"level":-69,"frequency":2437},"2c:36:f8:0f:fe:b4":{"SSID":"bld2-guest","capabilities":"[WEP][ESS]","timestamp":52987753641,"level":-69,"frequency":2437},"2c:36:f8:0f:fe:b2":{"SSID":"utroam","capabilities":"[WPA-PSK-CCMP][WPA2-PSK-CCMP][ESS]","timestamp":52987753622,"level":-71,"frequency":2437},"2c:36:f8:0f:fe:b7":{"SSID":"ist_members","capabilities":"[WPA2-PSK-CCMP][ESS]","timestamp":52987753647,"level":-71,"frequency":2437},"2c:36:f8:0f:fe:b8":{"SSID":"eng.ut-guest","capabilities":"[ESS]","timestamp":52987753612,"level":-67,"frequency":2437},"00:07:40:ed:62:04":{"SSID":"000740E604CF","capabilities":"[WEP][ESS]","timestamp":52980771809,"level":-77,"frequency":2422},"2c:36:f8:0f:fe:b5":{"SSID":"eng.ut-1x","capabilities":"[WPA2-EAP-CCMP][ESS]","timestamp":52987753655,"level":-66,"frequency":2437},"2c:36:f8:0f:fe:b6":{"SSID":"sanshiro","capabilities":"[WPA2-PSK-CCMP][ESS]","timestamp":52987753637,"level":-68,"frequency":2437},"10:bd:18:6d:e3:51":{"SSID":"utroam","capabilities":"[WPA-PSK-CCMP][WPA2-PSK-CCMP][ESS]","timestamp":52980771877,"level":-72,"frequency":2437},"32:f3:1d:4a:4b:5f":{"SSID":"EMOBILE-GL09P-4B5F","capabilities":"[WPA-PSK-CCMP+TKIP][WPA2-PSK-CCMP+TKIP][WPS][ESS]","timestamp":52980772124,"level":-77,"frequency":2437},"10:bd:18:6d:e3:52":{"SSID":"utroam-1x","capabilities":"[WPA2-EAP-CCMP][ESS]","timestamp":52987753595,"level":-72,"frequency":2437},"10:bd:18:6d:e3:50":{"SSID":"eng.ut","capabilities":"[WPA2-PSK-CCMP][ESS]","timestamp":52980771665,"level":-73,"frequency":2437},"10:bd:18:6d:e3:53":{"SSID":"ist_members","capabilities":"[WPA2-PSK-CCMP][ESS]","timestamp":52980772109,"level":-72,"frequency":2437},"00:1d:73:21:17:21":{"SSID":"ZENKIJIKKEN","capabilities":"[WEP][ESS]","timestamp":52987753617,"level":-65,"frequency":2422},"10:bd:18:6d:e3:54":{"SSID":"bld2-guest","capabilities":"[WEP][ESS]","timestamp":52987753651,"level":-71,"frequency":2437}},"magnetic":{"x":-12.832552,"y":18.498873,"z":-16.498993},"gravity":{"x":0.8842086,"y":4.6980224,"z":8.562413}},"location":{"floor":"4F","accuracy":0.5,"latitude":35.71433761427744,"longitude":139.76168777793646}},{"fingerprint":{"pressure":-1.0,"wifi":{"2c:36:f8:0f:da:90":{"SSID":"eng.ut","capabilities":"[WPA2-PSK-CCMP][ESS]","timestamp":52998478266,"level":-56,"frequency":2462},"2c:36:f8:0f:fb:80":{"SSID":"eng.ut","capabilities":"[WPA2-PSK-CCMP][ESS]","timestamp":52998477965,"level":-62,"frequency":2412},"00:1d:73:21:13:c0":{"SSID":"ZENKIJIKKEN","capabilities":"[WEP][ESS]","timestamp":52998477992,"level":-56,"frequency":2417},"2c:36:f8:0f:da:94":{"SSID":"bld2-guest","capabilities":"[WEP][ESS]","timestamp":52998478324,"level":-54,"frequency":2462},"2c:36:f8:0f:da:95":{"SSID":"eng.ut-1x","capabilities":"[WPA2-EAP-CCMP][ESS]","timestamp":52998478311,"level":-54,"frequency":2462},"2c:36:f8:0f:da:92":{"SSID":"utroam","capabilities":"[WPA-PSK-CCMP][WPA2-PSK-CCMP][ESS]","timestamp":52998478369,"level":-58,"frequency":2462},"00:20:a6:5d:64:0d":{"SSID":"yw6IUmTS","capabilities":"[WEP][ESS]","timestamp":52998478040,"level":-77,"frequency":2437},"2c:36:f8:0f:da:93":{"SSID":"utroam-1x","capabilities":"[WPA2-EAP-CCMP][ESS]","timestamp":52998478249,"level":-57,"frequency":2462},"2c:36:f8:0f:da:98":{"SSID":"eng.ut-guest","capabilities":"[ESS]","timestamp":52998478297,"level":-54,"frequency":2462},"2c:36:f8:0f:da:97":{"SSID":"ist_members","capabilities":"[WPA2-PSK-CCMP][ESS]","timestamp":52998478233,"level":-54,"frequency":2462},"3c:ce:73:49:7a:00":{"SSID":"eng.ut","capabilities":"[WPA2-PSK-CCMP][ESS]","timestamp":52998477914,"level":-72,"frequency":2412},"2c:36:f8:0f:fb:84":{"SSID":"bld2-guest","capabilities":"[WEP][ESS]","timestamp":52998477978,"level":-64,"frequency":2412},"3c:ce:73:49:7a:02":{"SSID":"utroam-1x","capabilities":"[WPA2-EAP-CCMP][ESS]","timestamp":52998477949,"level":-72,"frequency":2412},"3c:ce:73:49:7a:01":{"SSID":"utroam","capabilities":"[WPA-PSK-CCMP][WPA2-PSK-CCMP][ESS]","timestamp":52998478009,"level":-74,"frequency":2412},"3c:ce:73:49:7a:04":{"SSID":"bld2-guest","capabilities":"[WEP][ESS]","timestamp":52998477878,"level":-72,"frequency":2412},"2c:36:f8:0f:fe:b0":{"SSID":"eng.ut","capabilities":"[WPA2-PSK-CCMP][ESS]","timestamp":52998478090,"level":-70,"frequency":2437},"3c:ce:73:49:7a:03":{"SSID":"ist_members","capabilities":"[WPA2-PSK-CCMP][ESS]","timestamp":52987753570,"level":-62,"frequency":2412},"00:24:14:ff:f4:b1":{"SSID":"UTnet-wireless","capabilities":"[WPA2-PSK-CCMP][ESS]","timestamp":52998478283,"level":-70,"frequency":2462},"00:24:14:ff:f4:b2":{"SSID":"0001softbank","capabilities":"[ESS]","timestamp":52998478217,"level":-74,"frequency":2462},"04:fe:7f:93:6e:13":{"SSID":"upa48","capabilities":"[WPA2-PSK-CCMP][ESS]","timestamp":52987753590,"level":-81,"frequency":2437},"00:24:14:ff:f4:b6":{"SSID":"docomo","capabilities":"[WEP][ESS]","timestamp":52987753678,"level":-69,"frequency":2462},"2c:36:f8:0e:6b:22":{"SSID":"utroam","capabilities":"[WPA-PSK-CCMP][WPA2-PSK-CCMP][ESS]","timestamp":52998478353,"level":-85,"frequency":2437},"00:24:14:ff:f4:b3":{"SSID":"SWS1day","capabilities":"[ESS]","timestamp":52987753688,"level":-68,"frequency":2462},"2c:36:f8:0f:d3:28":{"SSID":"eng.ut-guest","capabilities":"[ESS]","timestamp":52998478124,"level":-86,"frequency":2437},"2c:36:f8:0e:6b:20":{"SSID":"eng.ut","capabilities":"[WPA2-PSK-CCMP][ESS]","timestamp":52998478339,"level":-91,"frequency":2437},"2c:36:f8:60:50:92":{"SSID":"utroam","capabilities":"[WPA-PSK-CCMP][WPA2-PSK-CCMP][ESS]","timestamp":52987753631,"level":-75,"frequency":2437},"2c:36:f8:60:50:90":{"SSID":"eng.ut","capabilities":"[WPA2-PSK-CCMP][ESS]","timestamp":52987753702,"level":-75,"frequency":2437},"2c:36:f8:60:50:91":{"SSID":"wnet.eng.ut","capabilities":"[WPA2-PSK-TKIP][ESS]","timestamp":52987753535,"level":-77,"frequency":2437},"00:24:14:ff:f4:b7":{"SSID":"0000docomo","capabilities":"[WPA2-PSK-CCMP][ESS]","timestamp":52987753673,"level":-63,"frequency":2462},"2c:36:f8:60:50:95":{"SSID":"eng.ut-guest","capabilities":"[ESS]","timestamp":52987753601,"level":-76,"frequency":2437},"00:20:a6:5d:87:01":{"SSID":"yw6IUmTS","capabilities":"[WEP][ESS]","timestamp":52998477932,"level":-79,"frequency":2412},"2c:36:f8:0f:fe:b3":{"SSID":"utroam-1x","capabilities":"[WPA2-EAP-CCMP][ESS]","timestamp":52998478185,"level":-64,"frequency":2437},"2c:36:f8:0f:fe:b4":{"SSID":"bld2-guest","capabilities":"[WEP][ESS]","timestamp":52987753641,"level":-69,"frequency":2437},"2c:36:f8:0f:fe:b2":{"SSID":"utroam","capabilities":"[WPA-PSK-CCMP][WPA2-PSK-CCMP][ESS]","timestamp":52987753622,"level":-71,"frequency":2437},"2c:36:f8:0f:fe:b7":{"SSID":"ist_members","capabilities":"[WPA2-PSK-CCMP][ESS]","timestamp":52998478156,"level":-65,"frequency":2437},"2c:36:f8:0f:fe:b8":{"SSID":"eng.ut-guest","capabilities":"[ESS]","timestamp":52998478105,"level":-74,"frequency":2437},"2c:36:f8:0f:fe:b5":{"SSID":"eng.ut-1x","capabilities":"[WPA2-EAP-CCMP][ESS]","timestamp":52998478071,"level":-63,"frequency":2437},"2c:36:f8:0f:fe:b6":{"SSID":"sanshiro","capabilities":"[WPA2-PSK-CCMP][ESS]","timestamp":52987753637,"level":-68,"frequency":2437},"10:bd:18:6d:e3:51":{"SSID":"utroam","capabilities":"[WPA-PSK-CCMP][WPA2-PSK-CCMP][ESS]","timestamp":52998478138,"level":-81,"frequency":2437},"10:bd:18:6d:e3:52":{"SSID":"utroam-1x","capabilities":"[WPA2-EAP-CCMP][ESS]","timestamp":52998478202,"level":-79,"frequency":2437},"10:bd:18:6d:e3:50":{"SSID":"eng.ut","capabilities":"[WPA2-PSK-CCMP][ESS]","timestamp":52998478172,"level":-81,"frequency":2437},"00:1d:73:21:17:21":{"SSID":"ZENKIJIKKEN","capabilities":"[WEP][ESS]","timestamp":52998478026,"level":-65,"frequency":2422},"10:bd:18:6d:e3:54":{"SSID":"bld2-guest","capabilities":"[WEP][ESS]","timestamp":52998478056,"level":-84,"frequency":2437}},"magnetic":{"x":-27.831636,"y":-5.166352,"z":-14.999086},"gravity":{"x":0.16983868,"y":5.459528,"z":8.144476}},"location":{"floor":"4F","accuracy":0.5,"latitude":35.71438960890172,"longitude":139.76168509572744}}]