[{"fingerprint":{"pressure":-1.0,"wifi":{"2c:36:f8:0f:fb:8d":{"SSID":"utroam","capabilities":"[WPA-PSK-CCMP][WPA2-PSK-CCMP][ESS]","timestamp":7832555217,"level":-70,"frequency":5240},"2c:36:f8:0f:fb:8f":{"SSID":"eng.ut","capabilities":"[WPA2-PSK-CCMP][ESS]","timestamp":7832555143,"level":-70,"frequency":5240},"2c:36:f8:0f:fb:80":{"SSID":"eng.ut","capabilities":"[WPA2-PSK-CCMP][ESS]","timestamp":7832555136,"level":-64,"frequency":2412},"2c:36:f8:0f:fb:83":{"SSID":"utroam-1x","capabilities":"[WPA2-EAP-CCMP][ESS]","timestamp":7832555127,"level":-65,"frequency":2412},"00:16:01:05:f8:ce":{"SSID":"ZENKIJIKKEN","capabilities":"[WEP][ESS]","timestamp":7832555512,"level":-82,"frequency":5220},"2c:36:f8:0f:da:92":{"SSID":"utroam","capabilities":"[WPA-PSK-CCMP][WPA2-PSK-CCMP][ESS]","timestamp":7822042365,"level":-59,"frequency":2462},"2c:36:f8:0f:da:9f":{"SSID":"eng.ut","capabilities":"[WPA2-PSK-CCMP][ESS]","timestamp":7832555272,"level":-72,"frequency":5180},"2c:36:f8:0f:da:99":{"SSID":"sanshiro","capabilities":"[WPA2-PSK-CCMP][ESS]","timestamp":7832555234,"level":-67,"frequency":5180},"2c:36:f8:0f:fb:88":{"SSID":"eng.ut-guest","capabilities":"[ESS]","timestamp":7832555243,"level":-66,"frequency":2412},"2c:36:f8:0f:da:98":{"SSID":"eng.ut-guest","capabilities":"[ESS]","timestamp":7832069082,"level":-56,"frequency":2462},"2c:36:f8:0f:fb:89":{"SSID":"sanshiro","capabilities":"[WPA2-PSK-CCMP][ESS]","timestamp":7832555174,"level":-70,"frequency":5240},"2c:36:f8:0f:da:97":{"SSID":"eng.ut-guest","capabilities":"[ESS]","timestamp":7832555207,"level":-70,"frequency":5180},"2c:36:f8:0f:fe:b0":{"SSID":"eng.ut","capabilities":"[WPA2-PSK-CCMP][ESS]","timestamp":7822042389,"level":-63,"frequency":2437},"2c:36:f8:0f:fb:87":{"SSID":"eng.ut-guest","capabilities":"[ESS]","timestamp":7832555225,"level":-70,"frequency":5240},"00:16:01:05:fc:7c":{"SSID":"ZENKIJIKKEN","capabilities":"[WEP][ESS]","timestamp":7832555432,"level":-79,"frequency":5220},"2c:36:f8:0f:fe:bc":{"SSID":"utroam-1x","capabilities":"[WPA2-EAP-CCMP][ESS]","timestamp":7832555443,"level":-81,"frequency":5220},"2c:36:f8:0f:cb:59":{"SSID":"sanshiro","capabilities":"[WPA2-PSK-CCMP][ESS]","timestamp":7832069476,"level":-92,"frequency":5220},"2c:36:f8:0f:fe:ba":{"SSID":"eng.ut-1x","capabilities":"[WPA2-EAP-CCMP][ESS]","timestamp":7832555403,"level":-80,"frequency":5220},"2c:36:f8:0f:fe:bb":{"SSID":"bld2-guest","capabilities":"[WEP][ESS]","timestamp":7832555502,"level":-82,"frequency":5220},"2c:36:f8:0f:d7:9f":{"SSID":"eng.ut","capabilities":"[WPA2-PSK-CCMP][ESS]","timestamp":7832069456,"level":-93,"frequency":5240},"2c:36:f8:0f:d7:9d":{"SSID":"utroam","capabilities":"[WPA-PSK-CCMP][WPA2-PSK-CCMP][ESS]","timestamp":7832555635,"level":-92,"frequency":5240},"2c:36:f8:0f:d7:9b":{"SSID":"bld2-guest","capabilities":"[WEP][ESS]","timestamp":7832069520,"level":-93,"frequency":5240},"2c:36:f8:0f:fe:b2":{"SSID":"utroam","capabilities":"[WPA-PSK-CCMP][WPA2-PSK-CCMP][ESS]","timestamp":7832069182,"level":-66,"frequency":2437},"2c:36:f8:0f:d7:97":{"SSID":"eng.ut-guest","capabilities":"[ESS]","timestamp":7832069461,"level":-93,"frequency":5240},"2c:36:f8:0f:cb:5d":{"SSID":"utroam","capabilities":"[WPA-PSK-CCMP][WPA2-PSK-CCMP][ESS]","timestamp":7832069471,"level":-92,"frequency":5220},"2c:36:f8:0f:fe:b7":{"SSID":"eng.ut-guest","capabilities":"[ESS]","timestamp":7832555473,"level":-83,"frequency":5220},"2c:36:f8:0f:fe:b8":{"SSID":"ist_members","capabilities":"[WPA2-PSK-CCMP][ESS]","timestamp":7832555463,"level":-81,"frequency":5220},"2c:36:f8:0f:d7:99":{"SSID":"sanshiro","capabilities":"[WPA2-PSK-CCMP][ESS]","timestamp":7832555647,"level":-92,"frequency":5240},"2c:36:f8:0f:da:9b":{"SSID":"bld2-guest","capabilities":"[WEP][ESS]","timestamp":7832555262,"level":-70,"frequency":5180},"2c:36:f8:0f:da:9c":{"SSID":"utroam-1x","capabilities":"[WPA2-EAP-CCMP][ESS]","timestamp":7832555290,"level":-72,"frequency":5180},"2c:36:f8:0f:da:9d":{"SSID":"utroam","capabilities":"[WPA-PSK-CCMP][WPA2-PSK-CCMP][ESS]","timestamp":7832555281,"level":-71,"frequency":5180},"2c:36:f8:0f:da:9a":{"SSID":"eng.ut-1x","capabilities":"[WPA2-EAP-CCMP][ESS]","timestamp":7832555190,"level":-70,"frequency":5180},"2c:36:f8:0f:fb:8b":{"SSID":"bld2-guest","capabilities":"[WEP][ESS]","timestamp":7832555252,"level":-70,"frequency":5240},"2c:36:f8:0f:fb:8c":{"SSID":"utroam-1x","capabilities":"[WPA2-EAP-CCMP][ESS]","timestamp":7832555156,"level":-70,"frequency":5240},"2c:36:f8:0f:fb:8a":{"SSID":"eng.ut-1x","capabilities":"[WPA2-EAP-CCMP][ESS]","timestamp":7832555165,"level":-70,"frequency":5240}},"magnetic":{"x":13.799439,"y":-25.798954,"z":-49.797977},"gravity":{"x":-1.5433623,"y":9.651027,"z":0.80325466}},"location":{"floor":"4F","accuracy":0.5,"latitude":35.714353131001324,"longitude":139.76172499358654}},{"fingerprint":{"pressure":-1.0,"wifi":{"2c:36:f8:0f:fb:8d":{"SSID":"utroam","capabilities":"[WPA-PSK-CCMP][WPA2-PSK-CCMP][ESS]","timestamp":7842973815,"level":-70,"frequency":5240},"2c:36:f8:0f:fb:8f":{"SSID":"eng.ut","capabilities":"[WPA2-PSK-CCMP][ESS]","timestamp":7842973780,"level":-70,"frequency":5240},"2c:36:f8:0f:fb:80":{"SSID":"eng.ut","capabilities":"[WPA2-PSK-CCMP][ESS]","timestamp":7842974068,"level":-66,"frequency":2412},"2c:36:f8:0f:fb:83":{"SSID":"utroam-1x","capabilities":"[WPA2-EAP-CCMP][ESS]","timestamp":7842288391,"level":-65,"frequency":2412},"00:16:01:05:f8:ce":{"SSID":"ZENKIJIKKEN","capabilities":"[WEP][ESS]","timestamp":7842974346,"level":-71,"frequency":5220},"2c:36:f8:0f:da:9f":{"SSID":"eng.ut","capabilities":"[WPA2-PSK-CCMP][ESS]","timestamp":7842973974,"level":-68,"frequency":5180},"2c:36:f8:0f:da:99":{"SSID":"sanshiro","capabilities":"[WPA2-PSK-CCMP][ESS]","timestamp":7842973929,"level":-66,"frequency":5180},"2c:36:f8:0f:fb:88":{"SSID":"eng.ut-guest","capabilities":"[ESS]","timestamp":7842288521,"level":-66,"frequency":2412},"2c:36:f8:0f:da:98":{"SSID":"eng.ut-guest","capabilities":"[ESS]","timestamp":7832069082,"level":-56,"frequency":2462},"2c:36:f8:0f:fb:89":{"SSID":"sanshiro","capabilities":"[WPA2-PSK-CCMP][ESS]","timestamp":7842973838,"level":-70,"frequency":5240},"2c:36:f8:0f:da:97":{"SSID":"eng.ut-guest","capabilities":"[ESS]","timestamp":7842974018,"level":-69,"frequency":5180},"2c:36:f8:0f:fe:b0":{"SSID":"eng.ut","capabilities":"[WPA2-PSK-CCMP][ESS]","timestamp":7842974110,"level":-69,"frequency":2437},"2c:36:f8:0f:fb:87":{"SSID":"eng.ut-guest","capabilities":"[ESS]","timestamp":7842973861,"level":-70,"frequency":5240},"00:16:01:05:fc:7c":{"SSID":"ZENKIJIKKEN","capabilities":"[WEP][ESS]","timestamp":7842974372,"level":-71,"frequency":5220},"2c:36:f8:0f:fe:bc":{"SSID":"utroam-1x","capabilities":"[WPA2-EAP-CCMP][ESS]","timestamp":7842974534,"level":-78,"frequency":5220},"2c:36:f8:0f:cb:59":{"SSID":"sanshiro","capabilities":"[WPA2-PSK-CCMP][ESS]","timestamp":7832069476,"level":-92,"frequency":5220},"2c:36:f8:0f:fe:b9":{"SSID":"sanshiro","capabilities":"[WPA2-PSK-CCMP][ESS]","timestamp":7842974692,"level":-78,"frequency":5220},"2c:36:f8:0f:fe:ba":{"SSID":"eng.ut-1x","capabilities":"[WPA2-EAP-CCMP][ESS]","timestamp":7842974560,"level":-77,"frequency":5220},"2c:36:f8:0f:fe:bb":{"SSID":"bld2-guest","capabilities":"[WEP][ESS]","timestamp":7842974745,"level":-78,"frequency":5220},"2c:36:f8:0f:d7:9f":{"SSID":"eng.ut","capabilities":"[WPA2-PSK-CCMP][ESS]","timestamp":7832069456,"level":-93,"frequency":5240},"2c:36:f8:0f:d7:9d":{"SSID":"utroam","capabilities":"[WPA-PSK-CCMP][WPA2-PSK-CCMP][ESS]","timestamp":7842288903,"level":-92,"frequency":5240},"2c:36:f8:0f:d7:9b":{"SSID":"bld2-guest","capabilities":"[WEP][ESS]","timestamp":7832069520,"level":-93,"frequency":5240},"2c:36:f8:0f:fe:b2":{"SSID":"utroam","capabilities":"[WPA-PSK-CCMP][WPA2-PSK-CCMP][ESS]","timestamp":7842974088,"level":-66,"frequency":2437},"2c:36:f8:0f:d7:97":{"SSID":"eng.ut-guest","capabilities":"[ESS]","timestamp":7832069461,"level":-93,"frequency":5240},"2c:36:f8:0f:cb:5d":{"SSID":"utroam","capabilities":"[WPA-PSK-CCMP][WPA2-PSK-CCMP][ESS]","timestamp":7832069471,"level":-92,"frequency":5220},"2c:36:f8:0f:fe:b7":{"SSID":"eng.ut-guest","capabilities":"[ESS]","timestamp":7842974585,"level":-78,"frequency":5220},"2c:36:f8:0f:fe:b8":{"SSID":"ist_members","capabilities":"[WPA2-PSK-CCMP][ESS]","timestamp":7842974719,"level":-76,"frequency":5220},"2c:36:f8:0f:d7:99":{"SSID":"sanshiro","capabilities":"[WPA2-PSK-CCMP][ESS]","timestamp":7842288914,"level":-92,"frequency":5240},"2c:36:f8:0f:da:9b":{"SSID":"bld2-guest","capabilities":"[WEP][ESS]","timestamp":7842974132,"level":-66,"frequency":5180},"2c:36:f8:0f:da:9c":{"SSID":"utroam-1x","capabilities":"[WPA2-EAP-CCMP][ESS]","timestamp":7842973907,"level":-67,"frequency":5180},"2c:36:f8:0f:da:9d":{"SSID":"utroam","capabilities":"[WPA-PSK-CCMP][WPA2-PSK-CCMP][ESS]","timestamp":7842973884,"level":-67,"frequency":5180},"2c:36:f8:0f:da:9a":{"SSID":"eng.ut-1x","capabilities":"[WPA2-EAP-CCMP][ESS]","timestamp":7842973997,"level":-69,"frequency":5180},"2c:36:f8:0f:fb:8b":{"SSID":"bld2-guest","capabilities":"[WEP][ESS]","timestamp":7842288530,"level":-70,"frequency":5240},"2c:36:f8:0f:fb:8c":{"SSID":"utroam-1x","capabilities":"[WPA2-EAP-CCMP][ESS]","timestamp":7842974612,"level":-76,"frequency":5240},"2c:36:f8:0f:fb:8a":{"SSID":"eng.ut-1x","capabilities":"[WPA2-EAP-CCMP][ESS]","timestamp":7842974639,"level":-76,"frequency":5240}},"magnetic":{"x":-0.59997565,"y":-14.399414,"z":-65.99732},"gravity":{"x":-1.9888334,"y":9.494955,"z":1.435324}},"location":{"floor":"4F","accuracy":0.5,"latitude":35.71433761427744,"longitude":139.76168777793646}},{"fingerprint":{"pressure":-1.0,"wifi":{"2c:36:f8:0f:fb:8d":{"SSID":"utroam","capabilities":"[WPA-PSK-CCMP][WPA2-PSK-CCMP][ESS]","timestamp":7852413559,"level":-70,"frequency":5240},"2c:36:f8:0f:fb:8f":{"SSID":"eng.ut","capabilities":"[WPA2-PSK-CCMP][ESS]","timestamp":7853124452,"level":-85,"frequency":5240},"2c:36:f8:0f:fb:80":{"SSID":"eng.ut","capabilities":"[WPA2-PSK-CCMP][ESS]","timestamp":7852413630,"level":-66,"frequency":2412},"2c:36:f8:0f:fb:83":{"SSID":"utroam-1x","capabilities":"[WPA2-EAP-CCMP][ESS]","timestamp":7842288391,"level":-65,"frequency":2412},"00:24:14:ff:f4:ba":{"SSID":"Wi2_club","capabilities":"[WPA2-PSK-CCMP][ESS]","timestamp":7853124033,"level":-79,"frequency":5240},"00:16:01:05:f8:ce":{"SSID":"ZENKIJIKKEN","capabilities":"[WEP][ESS]","timestamp":7852413783,"level":-71,"frequency":5220},"2c:36:f8:0f:da:9f":{"SSID":"eng.ut","capabilities":"[WPA2-PSK-CCMP][ESS]","timestamp":7853124485,"level":-81,"frequency":5180},"2c:36:f8:0f:da:99":{"SSID":"sanshiro","capabilities":"[WPA2-PSK-CCMP][ESS]","timestamp":7853124172,"level":-79,"frequency":5180},"2c:36:f8:0f:fb:88":{"SSID":"eng.ut-guest","capabilities":"[ESS]","timestamp":7842288521,"level":-66,"frequency":2412},"2c:36:f8:0f:da:98":{"SSID":"ist_members","capabilities":"[WPA2-PSK-CCMP][ESS]","timestamp":7853124197,"level":-79,"frequency":5180},"2c:36:f8:0f:fb:89":{"SSID":"sanshiro","capabilities":"[WPA2-PSK-CCMP][ESS]","timestamp":7852413585,"level":-70,"frequency":5240},"2c:36:f8:0f:da:97":{"SSID":"eng.ut-guest","capabilities":"[ESS]","timestamp":7853124602,"level":-81,"frequency":5180},"2c:36:f8:0f:fe:b0":{"SSID":"eng.ut","capabilities":"[WPA2-PSK-CCMP][ESS]","timestamp":7852413670,"level":-69,"frequency":2437},"2c:36:f8:0f:ce:6a":{"SSID":"eng.ut-1x","capabilities":"[WPA2-EAP-CCMP][ESS]","timestamp":7852415072,"level":-91,"frequency":5180},"2c:36:f8:0f:fb:87":{"SSID":"eng.ut-guest","capabilities":"[ESS]","timestamp":7852413608,"level":-70,"frequency":5240},"00:16:01:05:fc:7c":{"SSID":"ZENKIJIKKEN","capabilities":"[WEP][ESS]","timestamp":7853124811,"level":-84,"frequency":5220},"2c:36:f8:0f:fe:bc":{"SSID":"utroam-1x","capabilities":"[WPA2-EAP-CCMP][ESS]","timestamp":7853124659,"level":-82,"frequency":5220},"2c:36:f8:0f:fe:b9":{"SSID":"sanshiro","capabilities":"[WPA2-PSK-CCMP][ESS]","timestamp":7853124720,"level":-82,"frequency":5220},"2c:36:f8:0f:fe:ba":{"SSID":"eng.ut-1x","capabilities":"[WPA2-EAP-CCMP][ESS]","timestamp":7853124689,"level":-81,"frequency":5220},"2c:36:f8:0f:fe:bb":{"SSID":"bld2-guest","capabilities":"[WEP][ESS]","timestamp":7853124404,"level":-78,"frequency":5220},"00:24:14:ff:f4:b8":{"SSID":"0000docomo","capabilities":"[WPA2-PSK-CCMP][ESS]","timestamp":7853124055,"level":-80,"frequency":5240},"2c:36:f8:0f:d7:9f":{"SSID":"eng.ut","capabilities":"[WPA2-PSK-CCMP][ESS]","timestamp":7853125014,"level":-91,"frequency":5240},"2c:36:f8:0f:d7:9d":{"SSID":"utroam","capabilities":"[WPA-PSK-CCMP][WPA2-PSK-CCMP][ESS]","timestamp":7853125049,"level":-93,"frequency":5240},"2c:36:f8:0f:d7:9b":{"SSID":"bld2-guest","capabilities":"[WEP][ESS]","timestamp":7853125700,"level":-91,"frequency":5240},"2c:36:f8:0f:fe:b2":{"SSID":"utroam","capabilities":"[WPA-PSK-CCMP][WPA2-PSK-CCMP][ESS]","timestamp":7852413649,"level":-66,"frequency":2437},"2c:36:f8:0f:d7:97":{"SSID":"eng.ut-guest","capabilities":"[ESS]","timestamp":7853125192,"level":-91,"frequency":5240},"2c:36:f8:0f:fe:b7":{"SSID":"eng.ut-guest","capabilities":"[ESS]","timestamp":7853124244,"level":-78,"frequency":5220},"2c:36:f8:0f:fe:b8":{"SSID":"ist_members","capabilities":"[WPA2-PSK-CCMP][ESS]","timestamp":7853124122,"level":-80,"frequency":5220},"2c:36:f8:0f:d7:99":{"SSID":"sanshiro","capabilities":"[WPA2-PSK-CCMP][ESS]","timestamp":7853125134,"level":-93,"frequency":5240},"2c:36:f8:0f:da:9b":{"SSID":"bld2-guest","capabilities":"[WEP][ESS]","timestamp":7853124783,"level":-82,"frequency":5180},"2c:36:f8:0f:da:9c":{"SSID":"utroam-1x","capabilities":"[WPA2-EAP-CCMP][ESS]","timestamp":7853124544,"level":-82,"frequency":5180},"2c:36:f8:0f:da:9d":{"SSID":"utroam","capabilities":"[WPA-PSK-CCMP][WPA2-PSK-CCMP][ESS]","timestamp":7853124515,"level":-81,"frequency":5180},"2c:36:f8:0f:da:9a":{"SSID":"eng.ut-1x","capabilities":"[WPA2-EAP-CCMP][ESS]","timestamp":7853124574,"level":-81,"frequency":5180},"2c:36:f8:0f:fb:8b":{"SSID":"bld2-guest","capabilities":"[WEP][ESS]","timestamp":7853124897,"level":-89,"frequency":5240},"2c:36:f8:0f:fb:8c":{"SSID":"utroam-1x","capabilities":"[WPA2-EAP-CCMP][ESS]","timestamp":7853124751,"level":-82,"frequency":5240},"2c:36:f8:0f:fb:8a":{"SSID":"eng.ut-1x","capabilities":"[WPA2-EAP-CCMP][ESS]","timestamp":7852413829,"level":-76,"frequency":5240}},"magnetic":{"x":55.49775,"y":-8.399659,"z":-50.69794},"gravity":{"x":0.44861355,"y":9.525182,"z":2.2888567}},"location":{"floor":"4F","accuracy":0.5,"latitude":35.71432971980271,"longitude":139.76160932332277}}]